Workbook

Sheet Panel
B1: METAS VENTAS Y OCS 2026 MCLP
B2: Fecha actualización | C2: 46210
B4: Normativo | C4: Enero | D4: Febrero | F4: Marzo | G4: Abril | H4: Mayo | I4: Junio | J4: Julio | K4: Agosto | L4: Septiembre | M4: Octubre | N4: Noviembre | O4: Diciembre | P4: Total
B5: Meta acumulada | C5: 0 | D5: =C5+D6 -> 138 | F5: =D5+F6 -> 673 | G5: =F5+G6 -> 736.5 | H5: =G5+H6 -> 771.5 | I5: =H5+I6 -> 1081.1 | J5: =I5+J6 -> 1081.1 | K5: =J5+K6 -> 1081.1 | L5: =K5+L6 -> 2093.1 | M5: =L5+M6 -> 2513.1 | N5: =M5+N6 -> 2533.1 | O5: =N5+O6 -> 2533.1 | P5: =O5 -> 2533.1
B6: Proyección anual | C6: 0 | D6: 138 | F6: 535 | G6: 63.5 | H6: 35 | I6: 309.6 | J6: 0 | K6: 0 | L6: 1012 | M6: 420 | N6: 20 | O6: 0 | P6: =SUM(C6:O6) -> 2533.1
B7: OCs acumuladas | C7: =C8 -> 241.491 | D7: =C7+D8 -> 595.891 | F7: =D7+F8 -> 912.961 | G7: =F7+G8 -> 992.415 | H7: =G7+H8 -> 1482.877 | I7: =H7+I8 -> 1629.222
B8: OCs mensual | C8: =F79+F80+F81+F82+F84+F85+F86 -> 241.491 | D8: =(F89+F90+F92+F93+F94+F95) -> 354.4 | F8: =F97+F98+F100+F101+F102+F103+F104+F105+F106 -> 317.07 | G8: =F119 -> 79.454 | H8: =F121+F122+F124+F125+F126+F127+F129+F131+F132+F133+F134+F130 -> 490.462 | I8: =F137+F138+F139+F141+F143+F145 -> 146.345
B10: SCADAS Y SAC | C10: Enero | D10: Febrero | F10: Marzo | G10: Abril | H10: Mayo | I10: Junio | J10: Julio | K10: Agosto | L10: Septiembre | M10: Octubre | N10: Noviembre | O10: Diciembre | P10: Total
B11: Meta acumulada | C11: 0 | D11: =C11+D12 -> 58 | F11: =D11+F12 -> 133 | G11: =F11+G12 -> 313.8 | H11: =G11+H12 -> 367.5 | I11: =H11+I12 -> 447.5 | J11: =I11+J12 -> 696.5 | K11: =J11+K12 -> 951.5 | L11: =K11+L12 -> 1019 | M11: =L11+M12 -> 1138.5 | N11: =M11+N12 -> 1303.5 | O11: =N11+O12 -> 1303.5 | P11: =O11 -> 1303.5
B12: Proyección anual | C12: 0 | D12: 58 | F12: 75 | G12: 180.8 | H12: 53.7 | I12: 80 | J12: 249 | K12: 255 | L12: 67.5 | M12: 119.5 | N12: 165 | O12: 0 | P12: =SUM(C12:O12) -> 1303.5
B13: OCs acumuladas | C13: =C14 -> 37.98 | D13: =C13+D14 -> 37.98 | F13: =D13+F14 -> 46.256 | G13: =F13+G14 -> 46.256 | H13: =G13+H14 -> 50.039 | I13: =H13+I14 -> 50.039
B14: OCs mensual | C14: =F83 -> 37.98 | D14: 0 | F14: =F99 -> 8.276 | G14: 0 | H14: =F120 -> 3.783 | I14: 0
B16: PAC | C16: Enero | D16: Febrero | F16: Marzo | G16: Abril | H16: Mayo | I16: Junio | J16: Julio | K16: Agosto | L16: Septiembre | M16: Octubre | N16: Noviembre | O16: Diciembre | P16: Total
B17: Meta acumulada | C17: 0 | D17: =C17+D18 -> 498.7 | F17: =D17+F18 -> 569.8 | G17: =F17+G18 -> 591.8 | H17: =G17+H18 -> 749.5 | I17: =H17+I18 -> 766.4 | J17: =I17+J18 -> 766.4 | K17: =J17+K18 -> 766.4 | L17: =K17+L18 -> 1221.4 | M17: =L17+M18 -> 1299.4 | N17: =M17+N18 -> 1326.9 | O17: =N17+O18 -> 1326.9 | P17: =O17 -> 1326.9
B18: Proyección anual | C18: 0 | D18: 498.7 | F18: 71.1 | G18: 22 | H18: 157.7 | I18: 16.9 | J18: 0 | K18: 0 | L18: 455 | M18: 78 | N18: 27.5 | O18: 0 | P18: =SUM(C18:O18) -> 1326.9
B19: OCs acumuladas | C19: =C20 -> 13.339 | D19: =C19+D20 -> 132.639 | F19: =D19+F20 -> 132.639 | G19: =F19+G20 -> 132.639 | H19: =G19+H20 -> 174.218 | I19: =H19+I20 -> 227.078
B20: OCs mensual | C20: =F78+F87 -> 13.339 | D20: =F91 -> 119.3 | F20: 0 | G20: 0 | H20: =F123+F128+F135 -> 41.579 | I20: =F144+F146+F147+F148 -> 52.86
B22: PROCESOS (SISTEMAS Y SOLUCIONES) | C22: Enero | D22: Febrero | F22: Marzo | G22: Abril | H22: Mayo | I22: Junio | J22: Julio | K22: Agosto | L22: Septiembre | M22: Octubre | N22: Noviembre | O22: Diciembre | P22: Total
B23: Meta acumulada | C23: 0 | D23: =C23+D24 -> 0 | F23: =D23+F24 -> 0 | G23: =F23+G24 -> 0 | H23: =G23+H24 -> 0 | I23: =H23+I24 -> 0 | J23: =I23+J24 -> 0 | K23: =J23+K24 -> 150 | L23: =K23+L24 -> 150 | M23: =L23+M24 -> 750 | N23: =M23+N24 -> 900 | O23: =N23+O24 -> 1500 | P23: =O23 -> 1500
B24: Proyección anual | C24: 0 | D24: 0 | F24: 0 | G24: 0 | H24: 0 | I24: 0 | J24: 0 | K24: 150 | L24: 0 | M24: 600 | N24: 150 | O24: 600 | P24: =SUM(C24:O24) -> 1500
B25: OCs acumuladas | C25: 0 | D25: 0 | F25: 0 | G25: 0 | H25: 0 | I25: 0
B26: OCs mensual | C26: 0 | D26: 0 | F26: 0 | G26: 0 | H26: 0
B28: PROCESOS (ÁREA DE EQUIPOS) | C28: Enero | D28: Febrero | F28: Marzo | G28: Abril | H28: Mayo | I28: Junio | J28: Julio | K28: Agosto | L28: Septiembre | M28: Octubre | N28: Noviembre | O28: Diciembre | P28: Total
B29: Meta acumulada | C29: 0 | D29: =C29+D30 -> 0 | F29: =D29+F30 -> 0 | G29: =F29+G30 -> 0 | H29: =G29+H30 -> 0 | I29: =H29+I30 -> 0 | J29: =I29+J30 -> 0 | K29: =J29+K30 -> 0 | L29: =K29+L30 -> 0 | M29: =L29+M30 -> 0 | N29: =M29+N30 -> 0 | O29: =N29+O30 -> 0 | P29: =O29 -> 0
B30: Proyección anual | C30: 0 | D30: 0 | F30: 0 | G30: 0 | H30: 0 | P30: =SUM(C30:O30) -> 0
B31: OCs acumuladas | C31: 0 | D31: 0 | F31: 0 | G31: 0 | H31: 0
B32: OCs mensual | C32: 0 | D32: 0 | F32: 0 | G32: 0 | H32: 0
B49: TOTAL | C49: Enero | D49: Febrero | F49: Marzo | G49: Abril | H49: Mayo | I49: Junio | J49: Julio | K49: Agosto | L49: Septiembre | M49: Octubre | N49: Noviembre | O49: Diciembre | P49: Total
B50: Meta acumulada | C50: =C5+C11+C17+C23 -> 0 | D50: =D5+D11+D17+D23 -> 694.7 | F50: =F5+F11+F17+F23 -> 1375.8 | G50: =G5+G11+G17+G23 -> 1642.1 | H50: =H5+H11+H17+H23 -> 1888.5 | I50: =I5+I11+I17+I23 -> 2295 | J50: =J5+J11+J17+J23 -> 2544 | K50: =K5+K11+K17+K23 -> 2949 | L50: =L5+L11+L17+L23 -> 4483.5 | M50: =M5+M11+M17+M23 -> 5701 | ... O50: =O5+O11+O17+O23 -> 6663.5 | P50: 6664
B51: Proyección anual | C51: =C6+C12+C18+C24 -> 0 | D51: =D6+D12+D18+D24 -> 694.7 | F51: =F6+F12+F18+F24 -> 681.1 | G51: =G6+G12+G18+G24 -> 266.3 | H51: =H6+H12+H18+H24 -> 246.4 | I51: =I6+I12+I18+I24 -> 406.5 | J51: =J6+J12+J18+J24 -> 249 | K51: =K6+K12+K18+K24 -> 405 | L51: =L6+L12+L18+L24 -> 1534.5 | M51: =M6+M12+M18+M24 -> 1217.5 | ... O51: =O6+O12+O18+O24 -> 600
B52: OCs acumuladas | C52: =C7+C13+C19+C25 -> 292.81 | D52: =D7+D13+D19+D25 -> 766.51 | F52: =F7+F13+F19+F25 -> 1091.856 | G52: =G7+G13+G19+G25 -> 1171.31 | H52: =H7+H13+H19+H25 -> 1707.134 | I52: =I7+I13+I19+I25 -> 1906.339 | J52: =J7+J13+J19+J25 -> 0 | K52: =K7+K13+K19+K25 -> 0 | L52: =L7+L13+L19+L25 -> 0 | M52: =M7+M13+M19+M25 -> 0 | ... O52: =O7+O13+O19+O25 -> 0
B53: OCs mensual | C53: =C8+C14+C20+C26 -> 292.81 | D53: =D8+D14+D20+D26 -> 473.7 | F53: =F8+F14+F20+F26 -> 325.346 | G53: =G8+G14+G20+G26 -> 79.454 | H53: =H8+H14+H20+H26 -> 535.824 | I53: =I8+I14+I20+I26 -> 199.205 | J53: =J8+J14+J20+J26 -> 0 | K53: =K8+K14+K20+K26 -> 0 | L53: =L8+L14+L20+L26 -> 0 | M53: =M8+M14+M20+M26 -> 0 | ... O53: =O8+O14+O20+O26 -> 0
B76: Traspasos realizados: | E76: 40300
B77: Cliente | C77: OT | D77: VENTA EN UF | F77: VENTA EN M$ | G77: Costo Bruto M$ | H77: MB M$ | I77: Costo Neto M$ | J77: MN M$ | K77: Línea | L77: Descripcion
B78: Transelec | C78: 5153-03 | D78: 320 | F78: 13.067 | G78: 6.22 | H78: 6.847 | I78: 8.974 | J78: 4.092 | K78: PAC | L78: Integracion señales Quillota y Itahue | Q78: =H78/F78 -> 0.52399173
B79: Grenergy | C79: 5215-00 | D79: 2748 | F79: 109.172 | G79: 73.659 | H79: 35.514 | I79: 84.851 | J79: 24.32 | K79: Normativo | L79: Suministro Unidades de Medicion Sincrofasorial | Q79: =H79/F79 -> 0.32530319
B80: Agrosonda | C80: 5216-00 | D80: 1042 | F80: 41.397 | G80: 24.995 | H80: 16.765 | I80: 30.268 | J80: 11.128 | K80: Normativo | L80: Suministro e implementacion PMU y PDC PFV Planchón | Q80: =H80/F80 -> 0.40498104
B81: Arauco | C81: 5217-00 | D81: 1718 | F81: 69 | G81: 43.593 | H81: 25.54 | I81: 50.733 | J81: 17.518 | K81: Normativo | L81: Implementación de la PMU TG1 y TG3 PCNA (Nueva Aldea) | Q81: =H81/F81 -> 0.37014493
B82: Sigma | C82: 8375-01 | D82: 35.8 | F82: 1.422 | G82: 0.789 | H82: 0.633 | I82: 0.848 | J82: 0.574 | K82: Normativo | L82: Levantamiento y Diagnostico de RTU ABB 560 en instalaciones de ENAEX | Q82: =H82/F82 -> 0.44514768
B83: Colbun | C83: 8387-00 | D83: 956 | F83: 37.98 | G83: 12.605 | H83: 25.864 | I83: 24.537 | J83: 13.442 | K83: SCADA-SAC | L83: Integración PE Totoral a CCR | Q83: =H83/F83 -> 0.68098999
B84: Electrica Puntilla | C84: 8388-00 | D84: 159 | F84: 6.317 | G84: 1.878 | H84: 4.439 | I84: 3.923 | J84: 2.393 | K84: Normativo | L84: Ingenieria basica y detalle para la electrica puntilla | Q84: =H84/F84 -> 0.70270698
B85: Electrica Puntilla | C85: 8389-00 | D85: 198 | F85: 7.866 | G85: 2.598 | H85: 5.268 | I85: 5.039 | J85: 2.826 | K85: Normativo | L85: Ingenieria basica y detalle para la electrica Itata | Q85: =H85/F85 -> 0.66971777
B86: Soc Canal de Maipo | C86: 8390-00 | D86: 159 | F86: 6.317 | G86: 2.145 | H86: 4.172 | I86: 4.189 | J86: 2.126 | K86: Normativo | L86: Ingenieria basica y detalle para la Central Florida II | Q86: =H86/F86 -> 0.66044008
B87: Coop Reg Eléctrica Llanquihue | C87: 7081-00 | D87: 7 | F87: 0.272 | G87: 0.19 | H87: 0.82 | I87: 0.205 | J87: 0.66 | K87: PAC | L87: Suministro de Licencia Modubus Orion LX+ | Q87: =H87/F87 -> 3.0147059
B88: Ordenes de Compra Enero | D88: =SUM(D78:D87) -> 7342.8 | E88: =D88*$E$76 -> 295914840 | F88: =SUM(F78:F87) -> 292.81 | G88: =SUM(G78:G87) -> 168.672 | H88: =SUM(H78:H87) -> 125.862 | I88: =SUM(I78:I87) -> 213.567 | J88: =SUM(J78:J87) -> 79.079 | Q88: =H88/F88 -> 0.42984188
B89: Pacific Hydro | C89: 5218-00 | D89: 1259 | F89: 52 | G89: 28.4 | H89: 23.6 | I89: 36.5 | J89: 15.5 | K89: Normativo | L89: Suminisro e iplementacion PMU SE Chacayes y Pta Sierra | Q89: =H89/F89 -> 0.45384615
B90: CGE | C90: 5219-00 | D90: 2451 | F90: 97.3 | G90: 62.6 | H90: 35.7 | I90: 76.5 | J90: 21.9 | K90: Normativo | L90: Suminsitro e implemtacion PMU y block de pruebas | Q90: =H90/F90 -> 0.36690647
B91: Transelec | C91: 5220-00 | D91: 2962 | F91: 119.3 | G91: 61.6 | H91: 58.128 | I91: 89 | J91: 30.2 | K91: PAC | L91: Suministro y servicio de retrofit en la SSEE Ancoa | Q91: =H91/F91 -> 0.48724225
B92: Guacolda | C92: 5221-00 | D92: 2353.3 | F92: 93.4 | G92: 57.6 | H92: 37 | I92: 70 | J92: 23.9 | K92: Normativo | Q92: =H92/F92 -> 0.39614561
B93: Hidroelectrica La Higuera/Confluenza | C93: 5207-00 | D93: 2150 | F93: 85.4 | G93: 46.9 | H93: 39.4 | I93: 52.4 | J93: 32.9 | K93: Normativo | L93: Suministro 2 PMU La Higuera y Confluenza | Q93: =H93/F93 -> 0.46135831
B94: Agrosuper | C94: 8391-00 | D94: 67 | F94: 2.6 | G94: 1.3 | H94: 1.3 | I94: 2 | J94: 0.6 | K94: Normativo | L94: Servicio Levantamiento SITR SSEE | Q94: =H94/F94 -> 0.5
B95: Mantoverde | C95: 8392-00 | D95: 598 | F95: 23.7 | G95: 17.3 | H95: 6.4 | I95: 18.9 | J95: 4.7 | K95: Normativo | L95: Normalizacion señales SITR | Q95: =H95/F95 -> 0.27004219
B96: Ordenes de Compra Febrero | D96: =SUM(D89:D95) -> 11840.3 | E96: =D96*$E$76 -> 477164090 | F96: =SUM(F89:F95) -> 473.7 | G96: =SUM(G89:G95) -> 275.7 | H96: =SUM(H89:H95) -> 201.528 | I96: =SUM(I89:I95) -> 345.3 | J96: =SUM(J89:J95) -> 129.7 | Q96: =H96/F96 -> 0.42543382
B97: IO Integración de Sistemas | C97: 7082-00 | D97: 460 | F97: 17.5 | G97: 15.46 | H97: 1.875 | I97: 15.46 | J97: 1.875 | K97: Normativo | L97: Suministro de 7 Licencias PDC Corporativas | Q97: =H97/F97 -> 0.10714286
B98: Agrosonda | C98: 5205-01 | D98: 99 | F98: 3.933 | G98: 2.73 | H98: 1.202 | I98: 3.201 | J98: 0.731 | K98: Normativo | L98: Suministro y montaje de un inverson DC-AC | Q98: =H98/F98 -> 0.30561912
B99: Colbun | C99: 8352-01 | D99: 205 | F99: 8.276 | G99: 4.532 | H99: 3.744 | I99: 6.832 | J99: 1.443 | K99: SCADA-SAC | L99: Implementacion PMU Arauco TG8 y Cholguan | Q99: =H99/F99 -> 0.45239246
B100: Occidental | C100: 8393-00 | D100: 153 | F100: 6.078 | G100: 2.503 | H100: 3.576 | I100: 4.137 | J100: 1.942 | K100: Normativo | L100: Configurar las comunicaciones del SITR | Q100: =H100/F100 -> 0.58835143
B101: Celeo | C101: 8394-00 | D101: 806 | F101: 32.021 | G101: 3.718 | H101: 28.303 | I101: 6.523 | J101: 25.497 | K101: Normativo | L101: Servicio de Mantenimiento Preventivo 1er Semestre 2026 | Q101: =H101/F101 -> 0.8838887
B102: Cementos Melon | C102: 8395-00 | D102: 184 | F102: 7.31 | G102: 4.081 | H102: 3.229 | I102: 4.667 | J102: 2.643 | K102: Normativo | L102: Servicio Integración señales RTU | Q102: =H102/F102 -> 0.44172367
B103: Transelec | C103: 8396-00 | D103: 5223 | F103: 208 | G103: 124.038 | H103: 98.24 | I103: 151.774 | J103: 70.504 | K103: Normativo | L103: Modernizar los servidores de los 5 PDC Regionales de Transelec | Q103: =H103/F103 -> 0.47230769
B104: Aes Andes | C104: 8398-00 | D104: 200 | F104: 8.302 | G104: 4.604 | H104: 3.698 | I104: 5.576 | J104: 2.726 | K104: Normativo | L104: Suministro de licencias PDC, INTEGRACIÓN y pruebas de PMU | Q104: =H104/F104 -> 0.44543483
B105: Enlight | C105: 5222-00 | D105: 710 | F105: 28.207 | G105: 15.478 | H105: 12.729 | I105: 20.664 | J105: 7.543 | K105: Normativo | L105: Servicio de integeracion y suministro PMUparque fotovoltaico la Huayca | Q105: =H105/F105 -> 0.45127096
B106: Ibereolica | C106: 8336-01 | D106: 143 | F106: 5.719 | G106: 3.68 | H106: 2.039 | I106: 4.504 | J106: 1.215 | K106: Normativo | L106: Actualización Zenon | Q106: =H106/F106 -> 0.35653086
B107: Ordenes de Compra Marzo | D107: =SUM(D97:D106) -> 8183 | E107: =D107*$E$76 -> 329774900 | F107: =SUM(F97:F106) -> 325.346 | G107: =SUM(G97:G106) -> 180.824 | H107: =SUM(H97:H106) -> 158.635 | I107: =SUM(I97:I106) -> 223.338 | J107: =SUM(J97:J106) -> 116.119 | Q107: =H107/F107 -> 0.4875886
B108: Chiquinta Transmision | C108: 8397-00 | D108: 146 | F108: 5.85 | G108: 2.643 | H108: 3.207 | I108: 3.394 | J108: 2.456 | K108: Normativo | L108: Integración de PMU Cardones a PDC Chilquinta y a PDC CEN, m'as Licencia Corporativa | Q108: =H108/F108 -> 0.54820513
B109: Aes Andes | C109: 8399-00 | D109: 316 | F109: 12.325 | G109: 7.343 | H109: 4.981 | I109: 8.099 | J109: 4.225 | K109: Normativo | L109: Integracion PMU Los Cururos, donde se conectara la PMU al PDC | Q109: =H109/F109 -> 0.40413793
B110: Gassur S.A. | C110: 8400-00 | D110: 67 | F110: 2.696 | G110: 1.352 | H110: 1.345 | I110: 2.148 | J110: 0.548 | K110: Normativo | L110: Levantamiento Central Newen PMU | Q110: =H110/F110 -> 0.49888724
B111: Pacific Hydro | C111: 8401-00 | D111: 26 | F111: 1.046 | G111: 1.352 | H111: -0.305 | I111: 2.148 | J111: -1.101 | K111: Normativo | L111: Redirecionamiento PMU Chacayes | Q111: =H111/F111 -> -0.291587
B112: Fundicion talleres | C112: 8402-00 | D112: 140 | F112: 5.634 | G112: 1.931 | H112: 3.703 | I112: 3.871 | J112: 1.762 | K112: Normativo | L112: Modificacion direccion IP del SITR | Q112: =H112/F112 -> 0.6572595
B113: LAP | C113: 5155-01 | D113: 14 | F113: 0.536 | G113: 0.365 | H113: 0.17 | I113: 0.41 | J113: 0.125 | K113: Normativo | L113: Suministro SFP Transceiver RJ45 de Orion MX | Q113: =H113/F113 -> 0.31716418
B114: Transelec | C114: 5208-01 | D114: 309 | F114: 12.434 | G114: 10.45 | H114: 1.985 | I114: 10.51 | J114: 1.925 | K114: Normativo | L114: Subcontrato de cableado de señales TP y TC PMU Cerro Navia | Q114: =H114/F114 -> 0.15964291
B115: Minera Meridian | C115: 8365-01 | D115: 239 | F115: 9.685 | G115: 5.587 | H115: 4.099 | I115: 7.687 | J115: 1.999 | K115: Normativo | L115: Vereficación Rele EDAC | Q115: =H115/F115 -> 0.4232318
B116: Tecma | C116: 7083-00 | D116: 610 | F116: 24.374 | G116: 20.792 | H116: 3.582 | I116: 20.792 | J116: 3.582 | K116: Normativo | L116: Suministro 10 Licencia corporativa | Q116: =H116/F116 -> 0.14695988
B117: Hitachi Energy | C117: 7084-00 | D117: 61 | F117: 2.437 | G117: 2.079 | H117: 0.358 | I117: 2.079 | J117: 0.358 | K117: Normativo | L117: Suministro Licencia | Q117: =H117/F117 -> 0.14690193
B118: Siete Energya | C118: 7085-00 | D118: 61 | F118: 2.437 | G118: 2.079 | H118: 0.358 | I118: 2.079 | J118: 0.358 | K118: Normativo | L118: Suministro Licencia | Q118: =H118/F118 -> 0.14690193
B119: Ordenes de Compra Abril | D119: =SUM(D108:D118) -> 1989 | E119: =D119*$E$76 -> 80156700 | F119: =SUM(F108:F118) -> 79.454 | G119: =SUM(G108:G118) -> 55.973 | H119: =SUM(H108:H118) -> 23.483 | I119: =SUM(I108:I118) -> 63.217 | J119: =SUM(J108:J118) -> 16.237 | Q119: =H119/F119 -> 0.29555466
B120: GPE | C120: 8403-00 | D120: 94 | F120: 3.783 | G120: 1.19 | H120: 2.593 | I120: 3.075 | J120: 0.708 | K120: SCADA | L120: Integración Central Don Tito | Q120: =H120/F120 -> 0.68543484
B121: Alto Maipo | C121: 8404-00 | D121: 242 | F121: 9.427 | G121: 5.553 | H121: 3.874 | I121: 7.177 | J121: 2.25 | K121: Normativo | L121: Integración PMU Alfalfal | Q121: =H121/F121 -> 0.41094728
B122: Comasa | C122: 5209-01 | D122: 75 | F122: 3.061 | G122: 3.917 | H122: -0.857 | I122: 4.189 | J122: -1.128 | K122: Normativo | L122: Suministro de armarios | Q122: =H122/F122 -> -0.27997386
B123: Chilquinta Transmision | C123: 8408-00 | D123: 722 | F123: 29.053 | G123: 17.526 | H123: 11.527 | I123: 24.522 | J123: 4.531 | K123: PAC | L123: integración de un relé NR PCS-9611S y un medidor ION8650 | Q123: =H123/F123 -> 0.39675765
B124: Aes Andes | C124: 8399-01 | D124: 110 | F124: 4.426 | G124: 2.321 | H124: 2.106 | I124: 3.398 | J124: 1.028 | K124: Normativo | L124: cambio del GPS de la PMU Los Cururos | Q124: =H124/F124 -> 0.47582467
B125: Aes | C125: 8406-00 | D125: 721 | F125: 29.2 | G125: 18.819 | H125: 12.689 | I125: 20.565 | J125: 10.943 | K125: Normativo | L125: Integración de las PMU del Sur, 4 en total | Q125: =H125/F125 -> 0.43455479
B126: Aela Eolica Sarco | C126: 5125-02 | D126: 38 | F126: 1.529 | G126: 1.034 | H126: 0.495 | I126: 1.221 | J126: 0.308 | K126: Normativo | L126: Ejecucion de Pruebas Faltante PMU PE Sarco | Q126: =H126/F126 -> 0.32374101
B127: Aela Eolica Llanquihue | C127: 5126-01 | D127: 38 | F127: 1.529 | G127: 1.034 | H127: 0.495 | I127: 1.221 | J127: 0.308 | K127: Normativo | L127: Ejecucion de Pruebas Faltante PMU | Q127: =H127/F127 -> 0.32374101
B128: Tecnored | C128: 7086-00 | D128: 72 | F128: 2.895 | G128: 2.151 | H128: 0.744 | I128: 2.197 | J128: 0.698 | K128: PAC | L128: Suministro de GPS Kronos R2 | Q128: =H128/F128 -> 0.25699482
B129: Chilquinta | C129: 7087-00 | D129: 3116 | F129: 126.071 | G129: 98.297 | H129: 27.774 | I129: 98.698 | J129: 27.373 | K129: Normativo | L129: Suministro de 12 PMU Vizimax, 12 Licencias PDC Corporativo y 12 Licencias PDC Chilquinta | Q129: =H129/F129 -> 0.22030443
B130: Cia Minera Nevada | C130: 5223-00 | D130: 1051 | F130: 42.292 | G130: 27.146 | H130: 15.146 | I130: 32.26 | J130: 10.032 | K130: Normativo | L130: Suministro e implementacion TER Punta Colorada | Q130: =H130/F130 -> 0.3581292
B131: Saesa | C131: 5224-00 | D131: 1829 | F131: 73.152 | G131: 56.165 | H131: 16.987 | I131: 60.533 | J131: 12.619 | K131: Normativo | L131: Suministro de Servidor PDC con redundancia y licencias para 10 PMU | Q131: =H131/F131 -> 0.23221511
... B135: Litoral Transmision | C135: 5227-00 | D135: 241 | F135: 9.631 | G135: 5.241 | H135: 4.39 | I135: 6.445 | J135: 3.186 | K135: PAC | L135: Suministro de RTU Orion MX | Q135: =H135/F135 -> 0.45581975
B136: Ordenes de Compra Mayo | D136: =SUM(D120:D135) -> 13287 | E136: =D136*$E$76 -> 535466100 | F136: =SUM(F120:F135) -> 535.824 | G136: =SUM(G120:G135) -> 357.93 | H136: =SUM(H120:H135) -> 180.202 | I136: =SUM(I120:I135) -> 413.285 | J136: =SUM(J120:J135) -> 124.847 | Q136: =H136/F136 -> 0.33630819
B137: CGE | C137: 5219-01 | D137: 218 | F137: 8.772 | G137: 6.494 | H137: 2.279 | I137: 9.654 | J137: -0.881 | K137: Normativo | L137: Suministro de 3 Armarios Rittal | Q137: =H137/F137 -> 0.25980392
B138: Oxy | C138: 7088-00 | D138: 51 | F138: 2.052 | G138: 1.735 | H138: 0.317 | I138: 1.826 | J138: 0.226 | K138: Normativo | L138: Suministrar la licencia para el Firewall en Oxy | Q138: =H138/F138 -> 0.15448343
B139: Tecnored | C139: 7090-00 | D139: 124 | F139: 5.062 | G139: 4.171 | H139: 0.892 | I139: 4.232 | J139: 0.831 | K139: Normativo | L139: Suministro de 2 licencias PDC | Q139: =H139/F139 -> 0.17621493
B140: Tecma | C140: 7091-00 | D140: 511 | F140: 20.261 | G140: 17.294 | H140: 2.967 | I140: 17.294 | J140: 2.967 | K140: Normativo | L140: Licencias
B141: Enlasa | C141: 8405-00 | D141: 136 | F141: 5.473 | G141: 1.586 | H141: 3.887 | I141: 4.524 | J141: 0.949 | K141: Normativo | L141: variables, instalaciones y personal para ejecutar las pruebas | Q141: =H141/F141 -> 0.71021378
B142: Aes Andes | C142: 5225-01 | D142: 246 | F142: 10.048 | G142: 8.537 | H142: 1.511 | I142: 8.537 | J142: 1.511 | K142: Normativo | L142: Licencias PDC Corporativo x2 y PDC Local x 2
B143: Eletrans III | C143: 5226-00 | D143: 1644 | F143: 66.155 | G143: 32.625 | H143: 33.53 | I143: 39.628 | J143: 26.527 | K143: Normativo | L143: Suministro e implementación 2 PMU. | Q143: =H143/F143 -> 0.50684
B144: Transelec | C144: 8413-00 | D144: 109 | F144: 4.386 | G144: 1.726 | H144: 2.659 | I144: 3.237 | J144: 1.1489 | K144: PAC | L144: Integrar las señales de los desconectadores HT4 a la RTU Orion de Quillota | Q144: =H144/F144 -> 0.60624715
B145: Colbun | C145: 8414-00 | D145: 1462 | F145: 58.831 | G145: 22.658 | H145: 36.173 | I145: 49.54 | J145: 9.291 | K145: Normativo | L145: Levantamiento e ingeniería PMUs
B146: Engie | C146: 5214-01 | D146: 166 | F146: 6.625 | G146: 2.634 | H146: 3.991 | I146: 4.272 | J146: 2.3529 | K146: PAC | L146: Servicio de independización del núcleo de medición: | Q146: =H146/F146 -> 0.60241509
...

Sheet Proyección Q1 (Enero)
A1: Línea | B1: Oportunidad | C1: Cliente | D1: Vendedor | E1: Ingreso esperado | F1: Cierre esperado | G1: Etapa | H1: Probabilidad | I1: Ingreso con % | J1: Resultado Enero
A2: PAC | B2: Transelec - Retrofit de Protecciones | C2: TRANSELEC S A | D2: Kevin Fuentealba | E2: 120 | F2: 46052 | G2: Cierre 70% (Preferencia) | H2: 0.6 | I2: =E2*H2 -> 72 | J2: Se corre a Febrero
A3: Normativo | B3: Electrica Puntilla - Ingeniería Ing. Basica y de Detalle (7 PMUs) | D3: Francisco Catalan | E3: 20 | F3: 46053 | G3: Cierre 90% (Adjudicación Verbal) | H3: 0.9 | I3: =E3*H3 -> 18 | J3: OC
A4: SCADA | B4: Integración de 9 Protecciones al SCADA | C4: Codelco | D4: Franco Travaglini | E4: 10 | F4: 46112 | G4: Cierre 70% (Preferencia) | H4: 0.7 | I4: =E4*H4 -> 7
A5: Normativo | B5: acondicionamiento del SITR mantoverde | C5: MANTOS COPPER S.A. | D5: Francisco Catalan | E5: 25 | F5: 46080 | G5: Cierre 90% (Adjudicación Verbal) | H5: 0.9 | I5: =E5*H5 -> 22.5
A6: Normativo | B6: Codelco Gabriela Mistral - SLRP | D6: Franco Travaglini | E6: 39 | F6: 46112 | G6: Cierre 70% (Preferencia) | H6: 0.7 | I6: =E6*H6 -> 27.3
A7: PAC | B7: Reemplazo SAS Hualpén- Transelec | C7: TRANSELEC S A | D7: Kevin Fuentealba | E7: 736 | F7: 46080 | G7: Cierre 60% (CT Cubierto) | H7: 0.6 | I7: =E7*H7 -> 441.6
A8: Normativo | B8: PMU La Huayca | C8: Saferay | D8: Francisco Catalan | E8: 35 | F8: 46081 | G8: Cierre 60% (CT Cubierto) | H8: 0.6 | I8: =E8*H8 -> 21
A9: Normativo | B9: Visita de levantamiento | C9: Cementos Melon | D9: Francisco Catalan | E9: 3 | F9: 46081 | G9: Cierre 60% (CT Cubierto) | H9: 0.5 | I9: =E9*H9 -> 1.5
A10: Normativo | B10: Suministro e Integración 4 x PMU y 1 x PDC centralizado | C10: Statkraft | D10: Francisco Catalan | E10: 145 | F10: 46112 | G10: Cierre 70% (Preferencia) | H10: 0.5 | I10: =E10*H10 -> 72.5
A11: SCADA | B11: Servicios Reconectadores Fase 1 | C11: Chilquinta | D11: Franco Travaglini | E11: 50 | F11: 46081 | G11: Cierre 90% (Adjudicación Verbal) | H11: 0.9 | I11: =E11*H11 -> 45
A12: Normativo | B12: Implementación 6 PMUs | C12: Inkia | D12: Franco Travaglini | E12: 220 | F12: 46112 | G12: Cierre | H12: 0.5 | I12: =E12*H12 -> 110
A13: Normativo | B13: 5 x PMU de Sonnedix + PDC | C13: Sonnedix PMU | D13: Franco Travaglini | E13: 180 | F13: 46112 | G13: Cierre 70% (Preferencia) | H13: 0.7 | I13: =E13*H13 -> 126
A14: Normativo | B14: PMU - Eletrans | C14: Eletrans | D14: Franco Travaglini | E14: 86 | F14: 46112 | G14: Cierre 70% (Preferencia) | H14: 0.7 | I14: =E14*H14 -> 60.2
A15: Normativo | B15: PMU Campo lindo y PE San Matias | C15: AES | D15: Francisco Catalan | E15: 75 | F15: 46112 | G15: Cierre 90% (Adjudicación Verbal) | H15: 0.9 | I15: =E15*H15 -> 67.5
A16: Normativo | B16: Suministro 3 PMU TER - Esperanza | C16: Enorchile S.A. | D16: Francisco Catalan | E16: 73 | F16: 46112 | G16: Cierre | H16: 0.5 | I16: =E16*H16 -> 36.5
A17: Normativo | B17: Central Huasco (3 PMU) | D17: Franco Travaglini | E17: 95 | F17: 46112 | G17: Cierre 70% (Preferencia) | H17: 0.7 | I17: =E17*H17 -> 66.5
A18: Normativo | B18: PMU Mantos Blancos | C18: Diego Navarrete Lucero | D18: Kevin Fuentealba | E18: 70 | F18: 46112 | G18: Cierre | H18: 0.5 | I18: =E18*H18 -> 35
A19: SCADA | B19: Retrofit Protecciones y SCADA La Huayca | C19: Enlight | D19: Franco Travaglini | E19: 100 | F19: 46112 | G19: Cierre | H19: 0.3 | I19: =E19*H19 -> 30
A20: PAC | B20: Guacolda - Eficiencia Energetica | D20: Kevin Fuentealba | E20: 55 | F20: 46112 | G20: Cierre | H20: 0.5 | I20: =E20*H20 -> 27.5
G22: PROYECCIÓN INICIAL | H22: Enero | I22: =SUM(I2:I3) -> 90 | J22: 292
A23: Normativo | B23: Tinguiririca | H23: Febrero | I23: =SUM(I4:I11) -> 638.4
H24: Marzo | I24: =SUM(I12:I20) -> 559.2
H25: Total | I25: =SUM(I22:I24) -> 1287.6

Sheet Proyección Q1 (Febrero)
A1: Línea | B1: Oportunidad | C1: Cliente | D1: Vendedor | E1: Ingreso esperado | F1: Cierre esperado | G1: Etapa | H1: Probabilidad | I1: Ingreso con % | J1: Resultado Febrero | M1: Marzo | N1: Abril | O1: Mayo | P1: Junio | Q1: Julio | R1: Agosto | S1: Septiembre | T1: Octubre | U1: Noviembre | V1: Diciembre
A2: PAC | B2: Transelec - Retrofit de Protecciones | C2: TRANSELEC S A | D2: Kevin Fuentealba | E2: 120 | F2: 46066 | G2: Cierre 90% (Adjudicación Verbal) | H2: 0.9 | I2: =E2*H2 -> 108 | J2: OC
A3: SCADA | B3: Drivers Mantos Blancos | C3: MANTOS COPPER S.A. | D3: Franco Travaglini | E3: 12 | F3: 46079 | G3: Cierre | H3: 0.5 | I3: =E3*H3 -> 6 | J3: Se corre a Marzo
A4: PAC | B4: Reemplazo SAS Hualpén- Transelec | C4: TRANSELEC S A | D4: Kevin Fuentealba | E4: 736 | F4: 46080 | G4: Cierre 60% (CT Cubierto) | H4: 0.6 | I4: =E4*H4 -> 441.6 | J4: Perdido
A5: PAC | B5: Chilquinta - Suministro Relé NR SE Damascal | C5: Chilquinta | D5: Kevin Fuentealba | E5: 15 | F5: 46080 | G5: Cierre 60% (CT Cubierto) | H5: 0.6 | I5: =E5*H5 -> 9 | J5: Se corre a Marzo
A6: Normativo | B6: Visita de levantamiento | C6: Agrosuper | D6: Bruno Jofré | E6: 3 | F6: 46080 | G6: Cierre | H6: 0.9 | I6: =E6*H6 -> 2.7 | J6: OC
A7: Normativo | B7: Acondicionamiento del SITR | C7: Mantoverde | D7: Francisco Catalan | E7: 25 | F7: 46080 | G7: Cierre | H7: 1 | I7: =E7*H7 -> 25 | J7: OC
A8: Normativo | B8: Implementación 2 PMU | C8: Pacific Hydro | D8: Bruno Jofré | E8: 50 | F8: 46080 | G8: Cierre | H8: 1 | I8: =E8*H8 -> 50 | J8: OC
A9: Normativo | B9: Implementación 2 PMU | C9: Tinguiririca | D9: Bruno Jofré | E9: 91 | F9: 46080 | G9: Cierre | H9: 1 | I9: =E9*H9 -> 91 | J9: OC
A10: Normativo | B10: Visita de levantamiento | C10: Cementos Melon | D10: Francisco Catalan | E10: 3 | F10: 46081 | G10: Cierre 60% (CT Cubierto) | H10: 0.5 | I10: =E10*H10 -> 1.5 | J10: Sigue en Febrero
A11: PAC | B11: Trabajos adicionales Diego de Almagro | C11: Chilquinta | D11: Kevin Fuentealba | E11: 30 | F11: 46081 | G11: Cierre | H11: 1 | I11: =E11*H11 -> 30 | J11: Se corre a Marzo
A12: Normativo | B12: PMU La Huayca | C12: Saferay | D12: Francisco Catalan | E12: 35 | F12: 46112 | G12: Cierre 60% (CT Cubierto) | H12: 0.6 | I12: =E12*H12 -> 21
A13: Normativo | B13: Implementación 6 PMUs | C13: Inkia | D13: Franco Travaglini | E13: 220 | F13: 46112 | G13: Cierre | H13: 0.5 | I13: =E13*H13 -> 110
A14: Normativo | B14: 5 x PMU de Sonnedix + PDC | C14: Sonnedix PMU | D14: Franco Travaglini | E14: 180 | F14: 46112 | G14: Cierre 70% (Preferencia) | H14: 0.7 | I14: =E14*H14 -> 126
A15: Normativo | B15: PMU - Eletrans | C15: Eletrans | D15: Franco Travaglini | E15: 86 | F15: 46112 | G15: Cierre 70% (Preferencia) | H15: 0.7 | I15: =E15*H15 -> 60.2
A16: Normativo | B16: PMU Campo lindo y PE San Matias | C16: AES | D16: Francisco Catalan | E16: 75 | F16: 46112 | G16: Cierre 90% (Adjudicación Verbal) | H16: 0.9 | I16: =E16*H16 -> 67.5
A17: Normativo | B17: Suministro e Integración 4 x PMU y 1 x PDC centralizado | C17: Statkraft | D17: Francisco Catalan | E17: 145 | F17: 46112 | G17: Cierre 70% (Preferencia) | H17: 0.5 | I17: =E17*H17 -> 72.5
A18: Normativo | B18: Suministro 3 PMU TER - Esperanza | C18: Enorchile S.A. | D18: Francisco Catalan | E18: 73 | F18: 46112 | G18: Cierre | H18: 0.5 | I18: =E18*H18 -> 36.5
A19: Normativo | B19: Codelco Gabriela Mistral - SLRP | C19: Codelco | D19: Franco Travaglini | E19: 39 | F19: 46112 | G19: Cierre 70% (Preferencia) | H19: 0.7 | I19: =E19*H19 -> 27.3
A20: Normativo | B20: Central Huasco y Guacolda (3 PMU) + 5 integraciones | C20: Guacolda | D20: Franco Travaglini | E20: 100 | F20: 46112 | G20: Cierre 70% (Preferencia) | H20: 0.7 | I20: =E20*H20 -> 70
A21: Normativo | B21: PMU Mantos Blancos | C21: Diego Navarrete Lucero | D21: Kevin Fuentealba | E21: 70 | F21: 46112 | G21: Cierre | H21: 0.5 | I21: =E21*H21 -> 35
A22: Normativo | B22: Modernización Servidores PDC | C22: TRANSELEC S A | D22: Franco Travaglini | E22: 206 | F22: 46112 | G22: Cierre | H22: 0.9 | I22: =E22*H22 -> 185.4
A23: SCADA | B23: Integración de 9 Protecciones al SCADA | C23: Codelco | D23: Franco Travaglini | E23: 10 | F23: 46112 | G23: Cierre 70% (Preferencia) | H23: 0.7 | I23: =E23*H23 -> 7
... A28: PAC | B28: Servicios Reconectadores Fase 1 | C28: Chilquinta Distribución | D28: Kevin Fuentealba | E28: 50 | F28: 46112 | G28: Cierre 90% (Adjudicación Verbal) | H28: 0.9 | I28: =E28*H28 -> 45
M29: =SUM(M2:M28) -> 0 | N29: =SUM(N2:N28) -> 0 | O29: =SUM(O2:O28) -> 0 | P29: =SUM(P2:P28) -> 0 | Q29: =SUM(Q2:Q28) -> 0 | R29: =SUM(R2:R28) -> 0 | S29: =SUM(S2:S28) -> 0 | T29: =SUM(T2:T28) -> 0 | ... V29: =SUM(V2:V28) -> 0
G30: PROYECCIÓN ACTUALIZADA AL CIERRE DE ENERO | H30: Enero | I30: ='Proyección Q1 (Enero)'!J22 -> 292
H31: Febrero | I31: =SUM(I2:I11) -> 764.8 | J31: =Panel!F96 -> 473.7 | K31: =J31-I31 -> -291.1
H32: Marzo | I32: =SUM(I12:I28) -> 915.4
H33: Total | I33: =SUM(I30:I32) -> 1972.2

Sheet Proyección Q1 (Marzo)
A1: Línea | B1: Oportunidad | C1: Cliente | D1: Vendedor | E1: Ingreso esperado | F1: Cierre esperado | G1: Etapa | H1: Probabilidad | I1: Ingreso con % | J1: Resultado Marzo | N1: Mayo | O1: Junio | P1: Julio | Q1: Agosto | R1: Septiembre | S1: Octubre | T1: Noviembre | U1: Diciembre
A2: Normativo | B2: Suministro e Integración 4 x PMU y 1 x PDC centralizado | C2: Statkraft | D2: Francisco Catalan | E2: 145 | F2: 46112 | G2: Cierre 70% (Preferencia) | H2: 0.5 | I2: =E2*H2 -> 72.5 | J2: OC | N2: =I2*20% -> 14.5 | O2: =I2*25% -> 18.125 | R2: =I2*50% -> 36.25 | S2: =I2*5% -> 3.625
D3: Francisco Catalan | Q3: =H2*20.7 -> 10.35 | R3: =H2*3 -> 1.5 | S3: =H2*4.3 -> 2.15 | T3: =H2*4.5 -> 2.25
A4: Normativo | B4: PMU La Huayca | C4: Enlight Investments Spa | D4: Francisco Catalan | E4: 35 | F4: 46094 | G4: Cierre 60% (CT Cubierto) | H4: 0.6 | I4: =E4*H4 -> 21 | J4: OC
A5: Normativo | B5: Integración PMU Arrayan a Maitencillo | C5: Sonnedix Chile Holding S.p.A. | D5: Bruno Jofré | E5: 8 | F5: 46112 | G5: Cierre | H5: 0.3 | I5: =E5*H5 -> 2.4 | J5: Se corre a Abril
A6: Normativo | B6: Ampliación PDC 3 Licencias | C6: Acciona Energia Chile S.p.A. | D6: Franco Travaglini | E6: 10 | F6: 46112 | G6: Cierre | H6: 0.7 | I6: =E6*H6 -> 7 | J6: Se corre a Abril
A7: Normativo | B7: PDC SAESA | C7: Sociedad Austral de Electricidad S.A. | D7: Franco Travaglini | E7: 50 | F7: 46112 | G7: Cierre | H7: 0.5 | I7: =E7*H7 -> 25 | J7: Se corre a Abril
A8: Normativo | B8: Mtto PDCE 2026 | C8: CELEO REDES CHILE LIMITADA | D8: Franco Travaglini | E8: 64 | F8: 46112 | G8: Cierre 70% (Preferencia) | H8: 0.9 | I8: =E8*H8 -> 57.6 | J8: OC | N8: =I8*50% -> 28.8 | S8: =N8 -> 28.8
D9: Franco Travaglini
A10: Normativo | B10: IO - Licencias PDC | C10: IO | D10: Kevin Fuentealba | E10: 12 | F10: 46112 | G10: Cierre | H10: 0.9 | I10: =E10*H10 -> 10.8 | J10: OC | N10: =I10 -> 10.8
D11: Kevin Fuentealba | P11: =H10*10 -> 9
A12: Normativo | B12: Modernización Servidores PDC | C12: TRANSELEC S A | D12: Franco Travaglini | E12: 206 | F12: 46112 | G12: Cierre 60% (CT Cubierto) | H12: 0.9 | I12: =E12*H12 -> 185.4 | J12: OC | N12: =I12*15%*49% -> 13.6269 | O12: =I12*15%*49% -> 13.6269 | Q12: =I12*15%*49%+I12*51% -> 108.1809 | R12: =I12*20%*49% -> 18.1692 | S12: =I12*20%*49% -> 18.1692 | T12: =I12*10%*49% -> 9.0846 | U12: =I12*5%*49% -> 4.5423
D13: Franco Travaglini | O13: =H12*5.2 -> 4.68 | R13: =H12*78.4 -> 70.56 | S13: =O13 -> 4.68 | T13: =O13 -> 4.68 | U13: =O13 -> 4.68
A14: Scada | B14: Scada se magallanes | C14: ENAP | D14: Franco Travaglini | E14: 70 | F14: 46112 | G14: Cierre 60% (CT Cubierto) | H14: 0.6 | I14: =E14*H14 -> 42 | J14: ?
A15: PAC | B15: Chilquinta - Trabajos adicionales RTU SE DDA | C15: Chilquinta | D15: Kevin Fuentealba | E15: 31 | F15: 46112 | G15: Cierre 70% (Preferencia) | H15: 0.9 | I15: =E15*H15 -> 27.9 | J15: Se corre a Abril | N15: =I15/5 -> 5.58 | O15: =N15 -> 5.58 | P15: =O15 -> 5.58 | Q15: =P15 -> 5.58 | R15: =Q15 -> 5.58
D16: Kevin Fuentealba
A17: PAC | B17: Chilquinta - Suministro Relé NR SE Damascal | C17: Chilquinta | D17: Kevin Fuentealba | E17: 40 | F17: 46112 | G17: Cierre 60% (CT Cubierto) | H17: 0.6 | I17: =E17*H17 -> 24 | J17: Se corre a Mayo | N17: =I17*20% -> 4.8 | O17: =N17 -> 4.8 | P17: =O17 -> 4.8 | Q17: =I17*40% -> 9.6
D18: Kevin Fuentealba | Q18: =H17*2 -> 1.2 | R18: =H17*9.6 -> 5.76
A19: PAC | B19: Sigma & Enaex - Retrofit de RTU | C19: Sigma | D19: Kevin Fuentealba | E19: 60 | F19: 46112 | G19: Cierre 60% (CT Cubierto) | H19: 0.6 | I19: =E19*H19 -> 36 | J19: Se corre a Mayo | N19: =I19*20%*73% -> 5.256 | O19: =I19*20%*73%+I19*27% -> 14.976 | P19: =I19*20%*73% -> 5.256 | Q19: =I19*35%*73% -> 9.198 | R19: =I19*5%*73% -> 1.314
D20: Kevin Fuentealba | O20: =H19*0.6 -> 0.36 | Q20: =H19*12.4 -> 7.44
A21: PAC | B21: Transelec - Repro 2026 | C21: TRANSELEC S A | D21: Kevin Fuentealba | E21: 40 | F21: 46112 | G21: Cierre | H21: 0.1 | I21: =E21*H21 -> 4 | J21: Cancelado
D22: Kevin Fuentealba
A23: PAC | B23: Retrofit Protecciones La Huayca | C23: Enlight Investments Spa | D23: Kevin Fuentealba | E23: 100 | F23: 46112 | G23: Cierre | H23: 0.3 | I23: =E23*H23 -> 30 | J23: Se corre a Junio | M23: Presupuestario
D24: Kevin Fuentealba
A25: PAC | B25: TECK - Capacitación de protecciones | C25: Teck | D25: Kevin Fuentealba | E25: 10 | F25: 46112 | G25: Cierre | H25: 0.3 | I25: =E25*H25 -> 3 | J25: Se corre a Sept | O25: =I25 -> 3
D26: Kevin Fuentealba | O26: =H25*9 -> 2.7
A27: PAC | B27: Servicios Reconectadores Fase 1 | C27: Chilquinta Distribucion S.A. | D27: Kevin Fuentealba | E27: 30 | F27: 46112 | G27: Cierre 90% (Adjudicación Verbal) | H27: 0.9 | I27: =E27*H27 -> 27 | J27: Se corre a Abril | N27: =I27*20% -> 5.4 | O27: =I27*15% -> 4.05 | P27: =I27*20% -> 5.4 | S27: =I27*10% -> 2.7 | T27: =I27*30% -> 8.1 | U27: =I27*5% -> 1.35
D28: Kevin Fuentealba | O28: =H27*1.5 -> 1.35 | P28: =H27*2.8 -> 2.52 | R28: =O28 -> 1.35 | S28: =R28 -> 1.35 | T28: =S28 -> 1.35
G30: PROYECCIÓN ACTUALIZADA AL CIERRE DE MARZO | H30: Enero | I30: 292 | J30: =I30 -> 292 | M30: Ingresos | N30: =(N2+N4+N5+N6+N7+N8+N10+N12+N14+N15+N17+N19+N21+N23+N25+N27)*1000000 -> 88762900 | O30: =(O2+O4+O5+O6+O7+O8+O10+O12+O14+O15+O17+O19+O21+O23+O25+O27)*1000000 -> 64157900 | P30: =(P2+P4+P5+P6+P7+P8+P10+P12+P14+P15+P17+P19+P21+P23+P25+P27)*1000000 -> 21036000 | Q30: =(Q2+Q4+Q5+Q6+Q7+Q8+Q10+Q12+Q14+Q15+Q17+Q19+Q21+Q23+Q25+Q27)*1000000 -> 1.325589e+08 | R30: =(R2+R4+R5+R6+R7+R8+R10+R12+R14+R15+R17+R19+R21+R23+R25+R27)*1000000 -> 61313200 | S30: =(S2+S4+S5+S6+S7+S8+S10+S12+S14+S15+S17+S19+S21+S23+S25+S27)*1000000 -> 53294200 | T30: =(T2+T4+T5+T6+T7+T8+T10+T12+T14+T15+T17+T19+T21+T23+T25+T27)*1000000 -> 17184600 | U30: =(U2+U4+U5+U6+U7+U8+U10+U12+U14+U15+U17+U19+U21+U23+U25+U27)*1000000 -> 5892300
H31: Febrero | I31: ='Proyección Q1 (Febrero)'!J31 -> 473.7 | J31: =I31 -> 473.7 | M31: Egresos | N31: =(N3+N9+N11+N13+N16+N18+N20+N22+N24+N26+N28)*1000000 -> 0 | O31: =(O3+O9+O11+O13+O16+O18+O20+O22+O24+O26+O28)*1000000 -> 9090000 | P31: =(P3+P9+P11+P13+P16+P18+P20+P22+P24+P26+P28)*1000000 -> 11520000 | Q31: =(Q3+Q9+Q11+Q13+Q16+Q18+Q20+Q22+Q24+Q26+Q28)*1000000 -> 18990000 | R31: =(R3+R9+R11+R13+R16+R18+R20+R22+R24+R26+R28)*1000000 -> 79170000 | S31: =(S3+S9+S11+S13+S16+S18+S20+S22+S24+S26+S28)*1000000 -> 8180000 | T31: =(T3+T9+T11+T13+T16+T18+T20+T22+T24+T26+T28)*1000000 -> 8280000 | U31: =(U3+U9+U11+U13+U16+U18+U20+U22+U24+U26+U28)*1000000 -> 4680000
H32: Marzo | I32: =SUM(I2:I27) -> 575.6 | J32: =Panel!F107+K4+K8+K12 -> 325.346 | K32: =J32-I32 -> -250.254
H33: Total | I33: =SUM(I30:I32) -> 1341.3 | J33: =SUM(J30:J32) -> 1091.046
G35: Q1 | I35: Proyección Inicial | J35: Resultado
I36: ='Proyección Q1 (Enero)'!I25 -> 1287.6 | J36: =J33 -> 1091.046 | K36: =J36-I36 -> -196.554
A40: Normativo | B40: PMU | C40: Gas sur | D40: Bruno Jofré
A42: Normativo | B42: Ingeniería para implementación de 33 PMU | C42: Colbún | D42: Francisco Catalan | E42: 89 | F42: Abril | G42: Cotización | H42: 0.6 | I42: =E42*H42 -> 53.4 | O42: =I42*20% -> 10.68 | R42: =I42*40% -> 21.36 | U42: =I42*40% -> 21.36
P43: =H42*5 -> 3 | Q43: =P43 -> 3
A44: Normativo | B44: PMU | C44: Barrick | D44: Bruno Jofré | E44: 50 | F44: Mayo | G44: Cotización | H44: 0.5 | I44: =E44*H44 -> 25 | P44: =I44*20% -> 5 | Q44: =I44*25% -> 6.25 | T44: =I44*50% -> 12.5 | U44: =I44*5% -> 1.25
Q45: =0.9*H44 -> 0.45 | T45: =H44*15 -> 7.5 | U45: =H44*13 -> 6.5
A46: Equipos | C46: CPP | D46: Alfonso Calderón | E46: 254 | F46: Abril | G46: Cotización | H46: 0.5 | I46: =E46*H46 -> 127 | O46: =I46*30% -> 38.1 | P46: =(I46-O46)/3 -> 29.633333 | Q46: =P46 -> 29.633333 | R46: =Q46 -> 29.633333
O47: =H46*57 -> 28.5 | P47: =H46*46 -> 23 | Q47: =P47 -> 23 | R47: =Q47 -> 23 | T47: =H46*15 -> 7.5 | U47: =H46*13 -> 6.5

Sheet Proyección Q2 (Abril)
A1: Línea | B1: Oportunidad | C1: Cliente | D1: Vendedor | E1: Ingreso esperado | F1: Cierre esperado | G1: Etapa | H1: Probabilidad | I1: Ingreso con % | K1: Resultado Abril | M1: 0 | N1: Junio | O1: Julio | P1: Agosto | Q1: Septiembre | R1: Octubre | S1: Noviembre | T1: Diciembre
A2: Normativo | B2: implementación PMU | C2: Grupo Saesa | D2: Bruno Jofré | E2: 300 | F2: 46118 | G2: Cierre | H2: 0.6 | I2: =E2*H2 -> 180 | K2: Se corre a Mayo
A4: Normativo | B4: 2 x EDAG + 2 x PMU | C4: Southenergy Spa | D4: Bruno Jofré | E4: 120 | F4: 46129 | G4: Cotización | H4: 0.3
A6: SCADA | B6: SCADA Nova - SE | C6: ENAP | D6: Franco Travaglini | E6: 70 | F6: 46129 | G6: Cotización | H6: 0.5 | I6: =E6*H6*M1 -> 0 | N6: =I6/5 -> 0 | O6: =$N$6 -> 0 | P6: =$N$6 -> 0 | Q6: =$N$6 -> 0 | R6: =$N$6 -> 0
O7: =2.4*H6 -> 1.2 | P7: =8.5*H6 -> 4.25 | Q7: =H6*33 -> 16.5 | R7: =H6*4.9 -> 2.45
A8: Normativo | B8: Suministro Licencias PDC | C8: AES ANDES S.A. | D8: Franco Travaglini | E8: 19 | F8: 46142 | G8: Cotización | H8: 0.9
A10: Normativo | B10: Los Cururos implementacion de PMU | C10: AES ANDES S.A. | D10: Franco Travaglini | E10: 12 | F10: 46142 | G10: Cierre 70% (Preferencia) | H10: 0.7 | I10: =E10*H10 -> 8.4 | K10: OC
A12: Normativo | B12: Ingeniería 33 PMUs | C12: Colbun | D12: Francisco Catalan | E12: 100 | F12: 46142 | G12: Cierre 70% (Preferencia) | H12: 0.7 | I12: =E12*H12 -> 70 | K12: OC | L12: Falta traspaso | N12: =I12*20% -> 14 | Q12: =I12*40% -> 28 | T12: =I12*40% -> 28
O13: =3.5*H12 -> 2.45 | P13: =3.5*H12 -> 2.45
A14: Normativo | B14: PMU Santiago Solar | C14: EDF en Chile Holding SpA | D14: Bruno Jofré | E14: 27 | F14: 46142 | G14: Cotización | H14: 0.3
A16: Normativo | B16: Ampliación PDC 3 Licencias | C16: Acciona Energia Chile S.p.A. | D16: Franco Travaglini | E16: 10 | F16: 46142 | G16: Cierre 70% (Preferencia) | H16: 0.7 | I16: =E16*H16 -> 7 | K16: Se corre a Mayo
A18: Normativo | B18: PDC SAESA | C18: Sociedad Austral de Electricidad S.A. | D18: Franco Travaglini | E18: 50 | F18: 46142 | G18: Cierre 90% (Adjudicación Verbal) | H18: 0.9 | I18: =E18*H18 -> 45 | K18: Se corre a Mayo
A20: Normativo | B20: Mtto PDCE 2026 | C20: TRANSELEC S A | D20: Franco Travaglini | E20: 50 | F20: 46142 | G20: Cotización | H20: 0.7 | N20: =E20*H20/2 -> 17.5 | R20: =N20 -> 17.5
A22: Normativo | B22: EDAGxCE Conejo | C22: Sonnedix Chile Holding S.p.A. | D22: Bruno Jofré | E22: 25 | F22: 46142 | G22: Cotización | H22: 0.15
A24: Normativo | B24: Adicionales - montaje switch Ancud | C24: TRANSELEC S A | D24: Franco Travaglini | E24: 2 | F24: 46142 | G24: Cierre 70% (Preferencia) | H24: 0.7 | I24: =E24*H24 -> 1.4 | K24: Se corre a Noviembre
A26: Normativo | B26: SITR Linea 7 | C26: EMPRESA DE TRANSPORTES DE PASAJEROS METRO S.A. | D26: Franco Travaglini | E26: 22 | F26: 46142 | G26: Cierre | H26: 0.5 | I26: =E26*H26 -> 11 | K26: Se corre a Junio
A28: Normativo | B28: SLRP - Centralizado | C28: AES ANDES S.A | D28: Franco Travaglini | E28: 85 | F28: 46142 | G28: Cierre | H28: 0.5 | I28: =E28*H28 -> 42.5 | K28: Se corre a Mayo | N28: =I28*20% -> 8.5 | P28: =I28*25% -> 10.625 | R28: =I28*15% -> 6.375 | S28: =I28*10% -> 4.25 | T28: =I28*15% -> 6.375
P29: =5*H28 -> 2.5 | T29: =25*H28 -> 12.5
A30: SCADA | B30: Drivers Mantos Blancos | C30: MANTOS COPPER S.A. | D30: Franco Travaglini | E30: 12 | F30: 46142 | G30: Cierre | H30: 0.5 | I30: =E30*H30 -> 6 | K30: OC | L30: Falta traspaso
A32: PAC | B32: Chilquinta - Trabajos adicionales RTU SE DDA | C32: Chilquinta Transmisión S.A. | D32: Kevin Fuentealba | E32: 31 | F32: 46142 | G32: Cierre 90% (Adjudicación Verbal) | H32: 0.9 | I32: =E32*H32 -> 27.9 | K32: Falta traspaso
A34: PAC | B34: Dashboard de integración Medidores | C34: AES ANDES S.A. | D34: Franco Travaglini | E34: 3 | F34: 46142 | G34: Cierre | H34: 0.6 | I34: =E34*H34 -> 1.8 | K34: ? | L34: No aparece en embudo
A36: PAC | B36: Servicios Reconectadores Fase 1 | C36: Chilquinta Distribucion S.A. | D36: Kevin Fuentealba | E36: 40 | F36: 46142 | G36: Cierre 90% (Adjudicación Verbal) | H36: 0.9 | I36: =E36*H36 -> 36 | K36: Se corre a Mayo
A38: PAC | B38: Chilquinta - Suministro Relé NR SE Damascal | D38: Kevin Fuentealba | E38: 35 | F38: 46157 | G38: Cierre 90% (Adjudicación Verbal) | H38: 0.7 | I38: =E38*H38 -> 24.5
A40: Normativo | B40: SLRP y PDC Centro de Control | C40: Grenergy | D40: Franco Travaglini | E40: 250 | F40: 46170 | G40: Posicionamiento | H40: 0.5
A42: Normativo | B42: Implementación 2 PMUs | C42: X-elio | D42: Bruno Jofré | E42: 60 | F42: 46171 | G42: Cierre 60% (CT Cubierto) | H42: 0.7 | I42: =E42*H42 -> 42
A44: Normativo | B44: Implementación PMU | C44: Eletrans III S.A | D44: Kevin Fuentealba | E44: 80 | F44: 46171 | G44: Cotización | H44: 0.6 | P44: =E44*H44*20% -> 9.6 | Q44: =E44*H44*25% -> 12 | T44: =E44*H44*50% -> 24
O45: =H44*1.5 -> 0.9 | R45: =H44*2.5 -> 1.5 | S45: =H44*1.4 -> 0.84 | T45: =H44*23 -> 13.8
A46: Normativo | B46: Implementacion PDC | C46: ENORCHILE S.A. | D46: Bruno Jofré | E46: 70 | F46: 46171 | G46: Cotización | H46: 0.5
A48: Normativo | B48: Guacolda - Analisis y medción de calidad de energía | D48: Kevin Fuentealba | E48: 20 | F48: 46171 | G48: Cotización | H48: 0.6
A50: Normativo | B50: PMU Campo lindo y PE San Matias | C50: AES ANDES S.A. | D50: Francisco Catalan | E50: 75 | F50: 46171 | G50: Cierre | H50: 0.9 | I50: =E50*H50 -> 67.5 | J50: falta flujo
A52: Normativo | B52: Suministro e Integración 4 x PMU y 1 x PDC centralizado | C52: Statkraft | D52: Francisco Catalan | E52: 145 | F52: 46171 | G52: Cierre 70% (Preferencia) | H52: 0.5 | I52: =E52*H52 -> 72.5 | J52: falta flujo
A54: Normativo | B54: PMU Zona Centro | C54: TRANSELEC S A | D54: Franco Travaglini | E54: 160 | F54: 46171 | G54: Cotización | H54: 0.7 | Q54: =E54*H54*10% -> 11.2
P55: =1.3*H54 -> 0.91 | Q55: =0.4*H54 -> 0.28 | T55: =9.3*H54 -> 6.51
A56: Normativo | B56: Suministro e implementación PMU | C56: Minera American Barrick Ltda. | D56: Bruno Jofré | E56: 60 | F56: 46171 | G56: Cotización | H56: 0.5
A58: Normativo | B58: Edaltec - Implementación /Suministro PMU - Licencia PDC | D58: Kevin Fuentealba | E58: 30 | F58: 46171 | G58: Cierre | H58: 0.05 | I58: =E58*H58 -> 1.5
A60: Normativo | B60: Codelco Gabriela Mistral - SLRP | C60: Codelco Gabriela Mistral | D60: Franco Travaglini | E60: 39 | F60: 46171 | G60: Cierre 70% (Preferencia) | H60: 0.7 | I60: =E60*H60 -> 27.3
A62: Normativo | B62: Contrato Marco 15 PMU | C62: Chilquinta Transmisión S.A. | D62: Franco Travaglini | E62: 300 | F62: 46171 | G62: Cotización | H62: 0.6
A64: Normativo | B64: 2 x PMU Central Trineo y Maitencillo | C64: Siete Energía | D64: Franco Travaglini | E64: 70 | F64: 46171 | G64: Cierre | H64: 0.5 | I64: =E64*H64 -> 35
A66: Normativo | B66: SITR ENAEX - VERTICE CONSULTORES SPA | C66: SIGMA ENERGÍA SPA | D66: Bruno Jofré | E66: 21 | F66: 46171 | G66: Cierre | H66: 0.25 | I66: =E66*H66 -> 5.25
A68: Normativo | B68: PMU Mantos Blancos | C68: Mantos Cooper | D68: Kevin Fuentealba | E68: 70 | F68: 46171 | G68: Cierre | H68: 0.5 | I68: =E68*H68 -> 35
A70: PAC | B70: Chilquinta - Retrofit de RTU S/E Quilpue | D70: Kevin Fuentealba | E70: 60 | F70: 46171 | G70: Cotización | H70: 0.6
A72: PAC | B72: Yokogawa - Reemplazo RTU (9) GNL | C72: Yokogawa Electric | D72: Kevin Fuentealba | E72: 88 | F72: 46171 | G72: Posicionamiento | H72: 0.5
A74: PAC | B74: CMP - Mina el Romeral -Retrofit de protecciones | D74: Kevin Fuentealba | E74: 100 | F74: 46171 | G74: Posicionamiento | H74: 0.15
A76: PAC | B76: Sigma & Enaex - Retrofit de RTU | D76: Kevin Fuentealba | E76: 30 | F76: 46171 | G76: Cierre 60% (CT Cubierto) | H76: 0.6 | I76: =E76*H76 -> 18
A78: PAC | B78: Energía Pacifico - Retrofit 3 protecciones | D78: Kevin Fuentealba | E78: 26 | F78: 46171 | G78: Posicionamiento | H78: 0.25
A80: PAC | B80: Codelco Chuquicamata - Synchroteq SE 10A | D80: Kevin Fuentealba | E80: 35 | F80: 46171 | G80: Posicionamiento | H80: 0.15
A82: PAC | B82: Chilquinta Retrofit RTU Kingfisher S/E San pedro | D82: Kevin Fuentealba | E82: 50 | F82: 46171 | G82: Posicionamiento | H82: 0.25
A84: PAC | B84: Chilquinta - Retrofit RTU Kingfisher S/E San Torquemada | D84: Kevin Fuentealba | E84: 50 | F84: 46171 | G84: Posicionamiento | H84: 0.25
A86: PAC | B86: Chilquinta - Retrofit RTU SICAM S/E Peña Blanca | D86: Kevin Fuentealba | E86: 50 | F86: 46171 | G86: Posicionamiento | H86: 0.25
A88: PAC | B88: Delta-Electric - Servicios de Protecciones | D88: Kevin Fuentealba | E88: 10 | F88: 46171 | G88: Cierre | H88: 0 | I88: =E88*H88 -> 0
A90: PAC | B90: Sigma - Levantamiento EDAC y reemplazo de RTU Indura | D90: Kevin Fuentealba | E90: 40 | F90: 46171 | G90: Cierre | H90: 0 | I90: =E90*H90 -> 0
A92: PAC | B92: Guacolda - Mantenimiento Protecciones Termoelectrica Central Generador 1,2,3,4 y 5 | C92: Empresa Eléctrica Guacolda | D92: Kevin Fuentealba | E92: 40 | F92: 46171 | G92: Posicionamiento | H92: 0.25
A94: Normativo | B94: PMU - Eletrans | C94: Eletrans | D94: Franco Travaglini | E94: 86 | F94: 46172 | G94: Cierre 70% (Preferencia) | H94: 0.7 | I94: =E94*H94 -> 60.2
A96: PAC | B96: Tecnored - Actualización EDAC y Reemplazo RTU Inchalam | D96: Kevin Fuentealba | E96: 41 | F96: 46199 | G96: Cierre | H96: 0.15 | I96: =E96*H96 -> 6.15
A98: Normativo | B98: Implementación 4 PMUs | C98: ENORCHILE S.A. | D98: Bruno Jofré | E98: 100 | F98: 46203 | G98: Cierre | H98: 0.5 | I98: =E98*H98 -> 50
A100: Normativo | B100: Licitación Proyeto PMUs | C100: Innergex Energia Renovable S.p.A. | D100: Bruno Jofré | E100: 100 | F100: 46203 | G100: Cierre | H100: 0.5 | I100: =E100*H100 -> 50
A102: Normativo | B102: 5 x PMU de Sonnedix + PDC | C102: Sonnedix PMU | D102: Franco Travaglini | E102: 180 | F102: 46203 | G102: Cierre 70% (Preferencia) | H102: 0.7 | I102: =E102*H102 -> 126
A104: Normativo | B104: Ferrovial - 4 PMU Centella Transmisión | C104: Ingeniería y Montajes Ferrovial | D104: Kevin Fuentealba | E104: 120 | F104: 46203 | G104: Cierre | H104: 0.25 | I104: =E104*H104 -> 30
A106: Normativo | B106: licencia PDC Corporativo. | C106: REDEIA CORPORACION SA. | D106: Bruno Jofré | E106: 5.5 | F106: 46203 | G106: Cierre 90% (Adjudicación Verbal) | H106: 0.25 | I106: =E106*H106 -> 1.375
A108: Normativo | B108: LICENCIAS PDC Corportivo x 2 | C108: WPD Chile | D108: Francisco Catalan | E108: 4 | F108: 46203 | G108: Posicionamiento | H108: 0.3
A110: Normativo | B110: Edaltec - Licencias PDC | D110: Kevin Fuentealba | E110: 7 | F110: 46203 | G110: Cierre | H110: 0.5 | I110: =E110*H110 -> 3.5
A112: Normativo | B112: Soporte remoto configuración e instalación GPS | C112: VERTICE CONSULTORES SPA | D112: Bruno Jofré | E112: 1 | F112: 46203 | G112: Cierre 90% (Adjudicación Verbal) | H112: 0 | I112: =E112*H112 -> 0
A114: Normativo | B114: Vertice - Suministro GPS para EDAC ENAEX | C114: VERTICE CONSULTORES SPA | D114: Bruno Jofré | E114: 7 | F114: 46203 | G114: Posicionamiento | H114: 0.6
A116: SCADA | B116: Retrofit SCADA PE San Juan | C116: Colbun, Colbun | D116: Francisco Catalan | E116: 150 | F116: 46203 | G116: Posicionamiento | H116: 1 | J116: falta flujo
A118: SCADA | B118: Integración de 9 Protecciones al SCADA | C118: Codelco Gabriela Mistral | D118: Franco Travaglini | E118: 10 | F118: 46203 | G118: Cierre 70% (Preferencia) | H118: 0.7 | I118: =E118*H118 -> 7
A120: SCADA | B120: Servidor Redundante Centro de Control | C120: Gestion de Proyectos Electricos S.A. | D120: Francisco Catalan | E120: 39 | F120: 46203 | G120: Cierre 60% (CT Cubierto) | H120: 0.5 | I120: =E120*H120 -> 19.5 | J120: falta flujo
A122: SCADA | B122: Mantoverde - SCADA Integrador | D122: Franco Travaglini | E122: 150 | F122: 46203 | G122: Posicionamiento | H122: 0.3
A124: SCADA | B124: Control Compuertas - Rio Colorado | C124: GPE | D124: Franco Travaglini | E124: 17 | F124: 46203 | G124: Cierre | H124: 0.3 | I124: =E124*H124 -> 5.1
A126: PAC | B126: TEN - Suministro 2 RTU Orion + Configuración | D126: Kevin Fuentealba | E126: 30 | F126: 46203 | G126: Cierre | H126: 0.1 | I126: =E126*H126 -> 3
A128: PAC | B128: Chilquinta - Retrofit de RTU S/E Bosquemar | D128: Kevin Fuentealba | E128: 60 | F128: 46203 | G128: Posicionamiento | H128: 0
A130: PAC | B130: Retrofit Protecciones La Huayca | C130: Enlight Investments Spa | D130: Kevin Fuentealba | E130: 100 | F130: 46203 | G130: Cierre | H130: 0.3 | I130: =E130*H130 -> 30
G133: PROYECCIÓN INICIAL | H133: Abril | I133: =SUM(I2:I36) -> 437
H134: Mayo | I134: =SUM(I38:I95) -> 388.75
H135: Junio | I135: =SUM(I96:I130) -> 331.625
H136: Total | I136: =SUM(I133:I135) -> 1157.375
A140: Normativo | B140: PMU | C140: Barrick | D140: Bruno Jofré | E140: 50 | F140: Mayo | G140: Cotización | H140: 0.5 | I140: =E140*H140 -> 25 | P140: =I140*20% -> 5 | Q140: =I140*25% -> 6.25 | T140: =I140*50% -> 12.5 | U140: =I140*5% -> 1.25
Q141: =0.9*H140 -> 0.45 | T141: =H140*15 -> 7.5 | U141: =H140*13 -> 6.5
A142: Equipos | C142: CPP | D142: Alfonso Calderón | E142: 254 | F142: Abril | G142: Cotización | H142: 0 | I142: =E142*H142 -> 0 | O142: =I142*30% -> 0 | P142: =(I142-O142)/3 -> 0 | Q142: =P142 -> 0 | R142: =Q142 -> 0
O143: =H142*57 -> 0 | P143: =H142*46 -> 0 | Q143: =P143 -> 0 | R143: =Q143 -> 0 | T143: =H142*15 -> 0 | U143: =H142*13 -> 0
A144: Normativo | B144: 2 PMU | C144: Consorcio Santa Marta | D144: Francisco Catalán | E144: 55 | F144: 46171 | G144: Posicionamiento | H144: 0.1 | I144: =E144*H144 -> 5.5 | N144: =I144*20% -> 1.1 | O144: =I144*10% -> 0.55 | P144: =I144*20% -> 1.1 | Q144: =I144*25% -> 1.375 | R144: =I144*20% -> 1.1 | S144: =I144*5% -> 0.275
O145: =0.1*H144 -> 0.01 | Q145: =2.3*H144 -> 0.23 | R145: =H144*10 -> 1 | S145: =H144*6.2 -> 0.62
A146: Normativo | B146: Suministro 10 PMU y PDC | C146: Enlasa | D146: Francisco Catalán | E146: 237 | F146: 46203 | G146: Cierre | H146: 0.5 | I146: =E146*H146 -> 118.5 | P146: =I146*10% -> 11.85 | Q146: =I146*15% -> 17.775 | R146: =I146*20% -> 23.7 | T146: =I146*20% -> 23.7
O147: =1.4*H146 -> 0.7 | P147: =H146*2.6 -> 1.3 | R147: =21.5*H146 -> 10.75 | S147: =3.8*H146 -> 1.9 | T147: =H146*43.5 -> 21.75
A148: Scada | B148: Retrofit SCADA | C148: CPP | D148: Francisco Catalán | E148: 94 | F148: 46264 | G148: Cotización | H148: 0.3 | I148: =E148*H148 -> 28.2 | R148: =E148*H148*70%*35% -> 6.909 | S148: =65%*20%*E148*H148 -> 3.666 | T148: =E148*H148*65%*25% -> 4.5825
R149: =H148*0.3 -> 0.09 | S149: =R149 -> 0.09 | T149: =S149 -> 0.09
N150: =SUM(N3+N5+N7+N9+N11+N13+N15+N17+N19+N21+N23+N25+N27+N29+N31+N33+N35+N37+N39+N41+N43+N45+N47+N49+N51+N53+N55+N57+N59+N61+N63+N65+N67+N69+N71+N73+N75+N77+N79+N81+N83+N85+N87+N89+N91+N93+N95+N97+N99+N101+N103+N105+N107+N109+N111+N113+N115+N117+N119+N121+N123+N125+N127+N129+N131+N141+N143+N145+N147) -> 0 | O150: =SUM(O3+O5+O7+O9+O11+O13+O15+O17+O19+O21+O23+O25+O27+O29+O31+O33+O35+O37+O39+O41+O43+O45+O47+O49+O51+O53+O55+O57+O59+O61+O63+O65+O67+O69+O71+O73+O75+O77+O79+O81+O83+O85+O87+O89+O91+O93+O95+O97+O99+O101+O103+O105+O107+O109+O111+O113+O115+O117+O119+O121+O123+O125+O127+O129+O131+O141+O143+O145+O147) -> 5.26 | P150: =SUM(P3+P5+P7+P9+P11+P13+P15+P17+P19+P21+P23+P25+P27+P29+P31+P33+P35+P37+P39+P41+P43+P45+P47+P49+P51+P53+P55+P57+P59+P61+P63+P65+P67+P69+P71+P73+P75+P77+P79+P81+P83+P85+P87+P89+P91+P93+P95+P97+P99+P101+P103+P105+P107+P109+P111+P113+P115+P117+P119+P121+P123+P125+P127+P129+P131+P141+P143+P145+P147) -> 11.41 | Q150: =SUM(Q3+Q5+Q7+Q9+Q11+Q13+Q15+Q17+Q19+Q21+Q23+Q25+Q27+Q29+Q31+Q33+Q35+Q37+Q39+Q41+Q43+Q45+Q47+Q49+Q51+Q53+Q55+Q57+Q59+Q61+Q63+Q65+Q67+Q69+Q71+Q73+Q75+Q77+Q79+Q81+Q83+Q85+Q87+Q89+Q91+Q93+Q95+Q97+Q99+Q101+Q103+Q105+Q107+Q109+Q111+Q113+Q115+Q117+Q119+Q121+Q123+Q125+Q127+Q129+Q131+Q141+Q143+Q145+Q147) -> 17.46 | R150: =SUM(R3+R5+R7+R9+R11+R13+R15+R17+R19+R21+R23+R25+R27+R29+R31+R33+R35+R37+R39+R41+R43+R45+R47+R49+R51+R53+R55+R57+R59+R61+R63+R65+R67+R69+R71+R73+R75+R77+R79+R81+R83+R85+R87+R89+R91+R93+R95+R97+R99+R101+R103+R105+R107+R109+R111+R113+R115+R117+R119+R121+R123+R125+R127+R129+R131+R141+R143+R145+R147) -> 15.7 | S150: =SUM(S3+S5+S7+S9+S11+S13+S15+S17+S19+S21+S23+S25+S27+S29+S31+S33+S35+S37+S39+S41+S43+S45+S47+S49+S51+S53+S55+S57+S59+S61+S63+S65+S67+S69+S71+S73+S75+S77+S79+S81+S83+S85+S87+S89+S91+S93+S95+S97+S99+S101+S103+S105+S107+S109+S111+S113+S115+S117+S119+S121+S123+S125+S127+S129+S131+S141+S143+S145+S147) -> 3.36 | T150: =SUM(T3+T5+T7+T9+T11+T13+T15+T17+T19+T21+T23+T25+T27+T29+T31+T33+T35+T37+T39+T41+T43+T45+T47+T49+T51+T53+T55+T57+T59+T61+T63+T65+T67+T69+T71+T73+T75+T77+T79+T81+T83+T85+T87+T89+T91+T93+T95+T97+T99+T101+T103+T105+T107+T109+T111+T113+T115+T117+T119+T121+T123+T125+T127+T129+T131+T141+T143+T145+T147) -> 62.06
N152: =N149*1000000 -> 0 | O152: =O149*1000000 -> 0 | P152: =P149*1000000 -> 0 | Q152: =Q149*1000000 -> 0 | R152: =R149*1000000 -> 90000 | S152: =S149*1000000 -> 90000 | T152: =T149*1000000 -> 90000 | U152: =SUM(N152:T152) -> 270000
N153: =N150*1000000 -> 0 | O153: =O150*1000000 -> 5260000 | P153: =P150*1000000 -> 11410000 | Q153: =Q150*1000000 -> 17460000 | R153: =R150*1000000 -> 15700000 | S153: =S150*1000000 -> 3360000 | T153: =T150*1000000 -> 62060000 | U153: =SUM(N153:T153) -> 115250000

Sheet Proyección Q2 (Mayo)
A1: Línea | B1: Oportunidad | C1: Cliente | D1: Vendedor | E1: Ingreso esperado | F1: Cierre esperado | G1: Etapa | H1: Probabilidad | I1: Ingreso con % | K1: Resultado Mayo | M1: 0 | N1: Julio | O1: Agosto | P1: Septiembre | Q1: Octubre | R1: Noviembre | S1: Diciembre | T1: 46388
A2: Normativo | B2: 10 PMU Zona Cordillera | C2: AES ANDES S.A. | D2: Franco Travaglini | E2: 120 | F2: 46150 | G2: Cierre 90% (Adjudicación Verbal) | H2: 0.9 | I2: =E2*H2 -> 108 | K2: OC
I3: l
A4: Normativo | B4: 2 PMU | C4: Consorcio Santa Marta S.A. | D4: Francisco Catalan | E4: 55 | F4: 46157 | G4: Cierre | H4: 0.1 | I4: =E4*H4 -> 5.5 | K4: Se corre a Agosto | N4: =I4*20% -> 1.1 | O4: =I4*10% -> 0.55 | P4: =I4*20% -> 1.1 | Q4: =I4*25% -> 1.375 | R4: =I4*20% -> 1.1 | S4: =I4*5% -> 0.275
O5: =0.1*H4 -> 0.01 | Q5: =2.3*H4 -> 0.23 | R5: =H4*10 -> 1 | S5: =H4*6.2 -> 0.62
A6: Normativo | B6: PDC SAESA | C6: Sociedad Austral de Electricidad S.A. | D6: Franco Travaglini | E6: 70 | F6: 46157 | G6: Cierre 90% (Adjudicación Verbal) | H6: 0.9 | I6: =E6*H6 -> 63 | K6: OC | N6: =18%*H6*I6*20% -> 2.0412 | O6: =18%*H6*I6*10%+27%*H6*I6 -> 16.3296 | P6: =18%*H6*I6*50%+55%*H6*I6 -> 36.288 | Q6: =18%*H6*I6*20% -> 2.0412
I7: l | P7: =18*H6 -> 16.2 | Q7: =0.5*H6 -> 0.45 | R7: =33.6*H6 -> 30.24
A8: Normativo | B8: SLRP - Centralizado | C8: AES ANDES S.A. | D8: Franco Travaglini | E8: 100 | F8: 46164 | G8: Cierre 70% (Preferencia) | H8: 0.5 | I8: =E8*H8 -> 50 | K8: Perdido | N8: =I8*20% -> 10 | P8: =I8*25% -> 12.5 | R8: =I8*15% -> 7.5 | S8: =I8*10% -> 5 | T8: =I8*15% -> 7.5
I9: l | P9: =5*H8 -> 2.5 | T9: =25*H8 -> 12.5
A10: Normativo | B10: SLRP y PDC Centro de Control | C10: Grenergy | D10: Franco Travaglini | E10: 130 | F10: 46170 | G10: Cotización | H10: =50%*M1 -> 0 | I10: =E10*H10*$M$1 -> 0 | N10: =I10/5 -> 0 | O10: =$N$10 -> 0 | P10: =$N$10 -> 0 | Q10: =$N$10 -> 0 | R10: =$N$10 -> 0
I11: I
A12: SCADA | B12: Servicio arriendo de maleta omicron 356 - Synchroteq | C12: Engie Energia Chile S.A. | D12: Kevin Fuentealba | E12: 2 | F12: 46170 | G12: Cierre 90% (Adjudicación Verbal) | H12: 0.9 | I12: =E12*H12 -> 1.8 | K12: Se corre a Julio
A14: PAC | B14: Suministro GPS Kronos | C14: Tecnored S.A. | D14: Kevin Fuentealba | E14: 3 | F14: 46170 | G14: Cierre 90% (Adjudicación Verbal) | H14: 0.9 | I14: =E14*H14 -> 2.7 | K14: OC
A16: PAC | B16: Servicio de Independización de Nucleos | C16: Engie Energia Chile S.A. | D16: Kevin Fuentealba | E16: 7 | F16: 46170 | G16: Cierre 90% (Adjudicación Verbal) | H16: 0.9 | I16: =E16*H16 -> 6.3 | K16: Se corre a Julio
A18: Normativo | B18: Implementación 4 PMUs | C18: ENORCHILE S.A. | D18: Bruno Jofré | E18: 130 | F18: 46171 | G18: Cierre | H18: 0.5 | I18: =E18*H18 -> 65 | K18: Se corre a Junio | N18: =I18*10% -> 6.5 | O18: =I18*10% -> 6.5 | P18: =I18*15% -> 9.75 | R18: =I18*40% -> 26 | S18: =I18*15% -> 9.75 | T18: =I18*10% -> 6.5
I19: l | O19: =1.6*H18 -> 0.8 | R19: =19.8*H18 -> 9.9 | S19: =34.6*H18 -> 17.3 | T19: =H18*14.6 -> 7.3
A20: Normativo | B20: Eletrans Implementación 2 x PMU | C20: Eletrans III S.A | D20: Bruno Jofré | E20: 80 | F20: 46171 | G20: Cierre 70% (Preferencia) | H20: 0.7 | I20: =E20*H20 -> 56 | K20: Se corre a Junio | O20: =E20*H20*20% -> 11.2 | P20: =E20*H20*25% -> 14 | S20: =E20*H20*50% -> 28
I21: l | N21: =H20*1.5 -> 1.05 | Q21: =H20*2.5 -> 1.75 | R21: =H20*1.4 -> 0.98 | S21: =H20*23 -> 16.1
A22: Normativo | B22: Adecuación EDAC | C22: Eka Chile S.A. | D22: Kevin Fuentealba | E22: 12 | F22: 46171 | G22: Cierre | H22: 0.3 | I22: =E22*H22 -> 3.6 | K22: Se corre a Junio
A24: Normativo | B24: Suministro Gabinetes para PMU | C24: CGE TRANSMISION SA | D24: Bruno Jofré | E24: 20 | F24: 46171 | G24: Cotización | H24: 0.25 | I24: =E24*H24*$M$1 -> 0
A26: Normativo | B26: Integración de PMU Sarco y Aurora | C26: Innergex Energia Renovable S.p.A. | D26: Bruno Jofré | E26: 2 | F26: 46171 | G26: Cierre 60% (CT Cubierto) | H26: 0.7 | I26: =E26*H26 -> 1.4 | K26: Se corre a Julio
A28: Normativo | B28: PMU Domeyko | C28: VERANO EPC SPA | E28: 20 | F28: 46171 | G28: Cotización | H28: 0 | I28: =E28*H28*$M$1 -> 0
A30: Normativo | B30: Implementación 7 PMU | C30: Electrica Puntilla | D30: Franco Travaglini | E30: 140 | F30: 46171 | G30: Posicionamiento | H30: 0.7
A32: Normativo | B32: PMU Zona Centro | C32: TRANSELEC S A | D32: Franco Travaglini | E32: 160 | F32: 46171 | G32: Cierre | H32: 0.7 | I32: =E32*H32 -> 112 | K32: Se corre a Julio | O32: =I32*10% -> 11.2 | S32: =60%*I32 -> 67.2 | T32: =I32*30% -> 33.6
I33: l | N33: =1.4*H32 -> 0.98 | O33: =0.3*H32 -> 0.21 | R33: =9.2*H32 -> 6.44 | S33: =1.1*H32 -> 0.77 | T33: =17*H32 -> 11.9
A34: Normativo | B34: Ampliación PDC 3 Licencias | C34: Acciona Energia Chile S.p.A. | D34: Franco Travaglini | E34: 10 | F34: 46171 | G34: Cierre 70% (Preferencia) | H34: 0.7 | I34: =E34*H34 -> 7 | K34: Se corre a Junio
A36: Normativo | B36: 2 x EDAG + 2 x PMU | C36: Southenergy Spa | D36: Bruno Jofré | E36: 120 | F36: 46171 | G36: Cierre | H36: 0.3 | I36: =E36*H36 -> 36 | K36: Perdido
I37: l
A38: PAC | B38: Suministro RTU SE Balandras | C38: Tecnored S.A. | D38: Kevin Fuentealba | E38: 10 | F38: 46171 | G38: Cierre 90% (Adjudicación Verbal) | H38: 0.9 | I38: =E38*H38 -> 9 | K38: OC
A40: PAC | B40: Servicios Reconectadores Fase 1 | C40: Chilquinta Distribucion S.A. | D40: Kevin Fuentealba | E40: 40 | F40: 46171 | G40: Cierre 90% (Adjudicación Verbal) | H40: 0.9 | I40: =E40*H40 -> 36 | K40: Se corre a Junio
I41: l
A42: Normativo | B42: implementación 18 x PMU | C42: Grupo Saesa | D42: Franco Travaglini | E42: 300 | F42: 46172 | G42: Cierre 60% (CT Cubierto) | H42: 0.7 | I42: =E42*H42 -> 210 | K42: Se corre a Julio | N42: =I42*20% -> 42 | O42: =I42*10% -> 21 | P42: =I42*15% -> 31.5 | Q42: =I42*5% -> 10.5 | T42: =I42*21% -> 44.1 | U42: =I42*9% -> 18.9 | V42: =I42*20% -> 42
I43: l | O43: =1*H42 -> 0.7 | Q43: =9.9*H42 -> 6.93 | R43: =20*H42 -> 14 | S43: =76*H42 -> 53.2 | T43: =4.2*H42 -> 2.94 | U43: =4*H42 -> 2.8 | W43: =44*H42 -> 30.8
A44: SCADA | B44: SCADA Nova - CC | C44: ENAP | D44: Franco Travaglini | E44: 118 | F44: 46172 | G44: Cierre | H44: 0.5 | I44: =E44*H44 -> 59 | K44: Se corre a Junio | N44: =I44/5 -> 11.8 | O44: =$N$44 -> 11.8 | P44: =$N$44 -> 11.8 | Q44: =$N$44 -> 11.8 | R44: =$N$44 -> 11.8
I45: l | O45: =2.4*H44 -> 1.2 | P45: =8.5*H44 -> 4.25 | Q45: =H44*33 -> 16.5 | R45: =H44*4.9 -> 2.45
A46: Normativo | B46: Quantica - Licencias PDC | C46: QUANTICA INGENIERIA SPA | D46: Kevin Fuentealba | E46: 6 | F46: 46199 | G46: Cierre | H46: 0.5 | I46: =E46*H46 -> 3
A48: PAC | B48: Chilquinta - Retrofit de RTU S/E Quilpue | C48: Chilquinta Transmisión S.A. | D48: Kevin Fuentealba | E48: 60 | F48: 46199 | G48: Cotización | H48: 0.6 | I48: =E48*H48*$M$1 -> 0
I49: I
A50: PAC | B50: Servicios RTU SE Balandras | C50: Chilquinta Transmisión S.A. | D50: Kevin Fuentealba | E50: 20 | F50: 46199 | G50: Cierre 90% (Adjudicación Verbal) | H50: 0.9 | I50: =E50*H50 -> 18
I51: l
A52: PAC | B52: Tecnored - Actualización EDAC y Reemplazo RTU Inchalam | C52: Tecnored S.A. | D52: Kevin Fuentealba | E52: 41 | F52: 46199 | G52: Cierre | H52: 0.15 | I52: =E52*H52 -> 6.15
A54: Normativo | B54: Implementacion PDC | C54: ENORCHILE S.A. | D54: Bruno Jofré | E54: 70 | F54: 46203 | G54: Cotización | H54: 0.5 | I54: =E54*H54*$M$1 -> 0
I55: I
A56: Normativo | B56: Licitación Proyecto PMUs | C56: Innergex Energia Renovable S.p.A. | D56: Bruno Jofré | E56: 100 | F56: 46203 | G56: Cierre | H56: 0.5 | I56: =E56*H56 -> 50
I57: l
A58: Normativo | B58: Contrato Marco 15 PMU | C58: Chilquinta Transmisión S.A. | D58: Kevin Fuentealba | E58: 300 | F58: 46203 | G58: Cotización | H58: 0.6 | I58: =E58*H58*$M$1 -> 0
I59: I
A60: Normativo | B60: Suministro Licencias PDC | C60: Minera Escondida Limitada | D60: Bruno Jofré | E60: 5 | F60: 46203 | G60: Cotización | H60: 0.9 | I60: =E60*H60*$M$1 -> 0
A62: Normativo | B62: 5 x PMU de Sonnedix + PDC | C62: Sonnedix PMU | D62: Franco Travaglini | E62: 180 | F62: 46203 | G62: Cierre 70% (Preferencia) | H62: 0.7 | I62: =E62*H62 -> 126
I63: l
A64: Normativo | B64: Ferrovial - 4 PMU Centella Transmisión | C64: Ingeniería y Montajes Ferrovial | D64: Kevin Fuentealba | E64: 120 | F64: 46203 | G64: Cierre | H64: 0.5 | I64: =E64*H64 -> 60
I65: l
A66: Normativo | B66: Guacolda - Analisis y medción de calidad de energía | C66: Guacolda Energia SpA | D66: Kevin Fuentealba | E66: 20 | F66: 46203 | G66: Cierre 60% (CT Cubierto) | H66: 0.6 | I66: =E66*H66 -> 12
A68: Normativo | B68: licencia PDC Corporativo. | C68: REDEIA CORPORACION SA. | D68: Bruno Jofré | E68: 5.5 | F68: 46203 | G68: Cierre | H68: 0.25 | I68: =E68*H68 -> 1.375
A70: Normativo | B70: Suministro e Integración 4 x PMU y 1 x PDC centralizado | C70: Statkraft | D70: Francisco Catalan | E70: 145 | F70: 46203 | G70: Cierre | H70: 0.5 | I70: =E70*H70 -> 72.5
I71: l
A72: Normativo | B72: Integración PMU Norte | C72: AES ANDES S.A. | D72: Franco Travaglini | E72: 52 | F72: 46203 | G72: Cierre 70% (Preferencia) | H72: 0.7 | I72: =E72*H72 -> 36.4 | N72: =23%*I72*30%+77%*I72 -> 30.5396 | O72: =23%*I72*70% -> 5.8604
I73: l | P73: =H72*34 -> 23.8
A74: Normativo | B74: Suministro 10 PMU y PDC | C74: Energia Latina S.A. | D74: Francisco Catalan | E74: 250 | F74: 46203 | G74: Cierre | H74: 0.5 | I74: =E74*H74 -> 125
I75: l
A76: Normativo | B76: Suministro de licencias e integración 4 PMU | C76: AES ANDES S.A. | D76: Franco Travaglini | E76: 19 | F76: 46203 | G76: Cierre 70% (Preferencia) | H76: 0.9 | I76: =E76*H76 -> 17.1
A78: Normativo | B78: Mtto PDCE 2026 | C78: TRANSELEC S A | D78: Franco Travaglini | E78: 50 | F78: 46203 | G78: Cotización | H78: 0.7 | I78: =E78*H78*$M$1 -> 0 | O78: =I78/2 -> 0 | R78: =O78 -> 0
I79: I
A80: Normativo | B80: LICENCIAS PDC Corportivo x 2 | C80: WPD Chile | D80: Francisco Catalan | E80: 4 | F80: 46203 | G80: Posicionamiento | H80: 0.3 | P80: =E80*H80*20% -> 0.24 | Q80: =E80*H80*25% -> 0.3 | T80: =E80*H80*50% -> 0.6
A82: Normativo | B82: Suministro 1 PMU TER - Esperanza | C82: Enorchile S.A. | D82: Francisco Catalan | E82: 30 | F82: 46203 | G82: Cierre | H82: 0.5 | I82: =E82*H82 -> 15
A84: Normativo | B84: SITR Linea 7 | C84: EMPRESA DE TRANSPORTES DE PASAJEROS METRO S.A. | D84: Franco Travaglini | E84: 22 | F84: 46203 | G84: Cierre 70% (Preferencia) | H84: 0.5 | I84: =E84*H84 -> 11
A86: Normativo | B86: Vertice - Suministro GPS para EDAC ENAEX | C86: VERTICE CONSULTORES SPA | D86: Bruno Jofré | E86: 7 | F86: 46203 | G86: Posicionamiento | H86: 0.6
A88: Normativo | B88: OPAL - UCH | C88: Universidad de Chile | D88: Francisco Catalan | E88: 17 | F88: 46203 | G88: Cierre | H88: 0.15 | I88: =E88*H88 -> 2.55
A90: Normativo | B90: PMU Mantos Blancos | C90: Mantos Cooper | D90: Francisco Catalan | E90: 70 | F90: 46203 | G90: Cierre | H90: 0.5 | I90: =E90*H90 -> 35
I91: l
A92: SCADA | B92: Mantoverde - SCADA Integrador | C92: Mantoverde S.A. | D92: Franco Travaglini | E92: 150 | F92: 46203 | G92: Posicionamiento | H92: 0.3
A94: PAC | B94: Retrofit RTU SE Reñaca | C94: Chilquinta Transmisión S.A. | D94: Kevin Fuentealba | E94: 50 | F94: 46203 | G94: Cotización | H94: 0.6 | I94: =E94*H94*$M$1 -> 0
I95: I
A96: PAC | B96: RTU - SE Laberinto | C96: Chilquinta Transmisión S.A. | D96: Kevin Fuentealba | E96: 80 | F96: 46203 | G96: Cotización | H96: 0.6 | I96: =E96*H96*$M$1 -> 0
I97: I
A98: PAC | B98: TEN - Suministro 2 RTU Orion + Configuración | C98: Transmisora Electrica Del Norte S.A. | D98: Kevin Fuentealba | E98: 30 | F98: 46203 | G98: Cierre | H98: 0.1 | I98: =E98*H98 -> 3
G101: PROYECCIÓN ACTUALIZADA AL CIERRE DE ABRIL | H101: Abril | I101: ='Proyección Q2 (Abril)'!I133 -> 437 | J101: =Panel!F119 -> 79.454 | K101: =J101-I101 -> -357.546 | N101: =(N2+N6+N8+N10+N18+N20+N32+N36+N40+N42+N44+N48+N50+N54+N56+N58+N62+N64+N70+N72+N74+N78+N90+N94+N96)*1000000 -> 102880800 | O101: =(O2+O6+O8+O10+O18+O20+O32+O36+O40+O42+O44+O48+O50+O54+O56+O58+O62+O64+O70+O72+O74+O78+O90+O94+O96)*1000000 -> 83890000 | P101: =(P2+P6+P8+P10+P18+P20+P32+P36+P40+P42+P44+P48+P50+P54+P56+P58+P62+P64+P70+P72+P74+P78+P90+P94+P96)*1000000 -> 1.15838e+08 | Q101: =(Q2+Q6+Q8+Q10+Q18+Q20+Q32+Q36+Q40+Q42+Q44+Q48+Q50+Q54+Q56+Q58+Q62+Q64+Q70+Q72+Q74+Q78+Q90+Q94+Q96)*1000000 -> 24341200 | R101: =(R2+R6+R8+R10+R18+R20+R32+R36+R40+R42+R44+R48+R50+R54+R56+R58+R62+R64+R70+R72+R74+R78+R90+R94+R96)*1000000 -> 45300000 | S101: =(S2+S6+S8+S10+S18+S20+S32+S36+S40+S42+S44+S48+S50+S54+S56+S58+S62+S64+S70+S72+S74+S78+S90+S94+S96)*1000000 -> 109950000 | T101: =(T2+T6+T8+T10+T18+T20+T32+T36+T40+T42+T44+T48+T50+T54+T56+T58+T62+T64+T70+T72+T74+T78+T90+T94+T96)*1000000 -> 91700000 | U101: =SUM(N101:T101) -> 573900000
H102: Mayo | I102: =SUM(I2:I44) -> 832.3 | J102: =Panel!F136 -> 535.824 | K102: =J102-I102 -> -296.476 | N102: =(N3+N7+N9+N11+N19+N21+N33+N37+N41+N43+N45+N49+N51+N55+N57+N59+N63+N65+N71+N73+N75+N79+N91+N95+N97)*1000000 -> 2030000 | O102: =(O3+O7+O9+O11+O19+O21+O33+O37+O41+O43+O45+O49+O51+O55+O57+O59+O63+O65+O71+O73+O75+O79+O91+O95+O97)*1000000 -> 2910000 | P102: =(P3+P7+P9+P11+P19+P21+P33+P37+P41+P43+P45+P49+P51+P55+P57+P59+P63+P65+P71+P73+P75+P79+P91+P95+P97)*1000000 -> 46750000 | Q102: =(Q3+Q7+Q9+Q11+Q19+Q21+Q33+Q37+Q41+Q43+Q45+Q49+Q51+Q55+Q57+Q59+Q63+Q65+Q71+Q73+Q75+Q79+Q91+Q95+Q97)*1000000 -> 25630000 | R102: =(R3+R7+R9+R11+R19+R21+R33+R37+R41+R43+R45+R49+R51+R55+R57+R59+R63+R65+R71+R73+R75+R79+R91+R95+R97)*1000000 -> 64010000 | S102: =(S3+S7+S9+S11+S19+S21+S33+S37+S41+S43+S45+S49+S51+S55+S57+S59+S63+S65+S71+S73+S75+S79+S91+S95+S97)*1000000 -> 87370000 | T102: =(T3+T7+T9+T11+T19+T21+T33+T37+T41+T43+T45+T49+T51+T55+T57+T59+T63+T65+T71+T73+T75+T79+T91+T95+T97)*1000000 -> 34640000 | U102: =SUM(N102:T102) -> 263340000
H103: Junio | I103: =SUM(I46:I98) -> 594.075
A105: Normativo | B105: PMU | C105: Barrick | D105: Bruno Jofré | E105: 42 | F105: Mayo | G105: Cierre | H105: 0.9 | I105: =E105*H105 -> 37.8 | N105: =I105*20% -> 7.56 | O105: =I105*25% -> 9.45 | R105: =I105*50% -> 18.9 | S105: =I105*5% -> 1.89
O106: =0.9*H105 -> 0.81 | R106: =H105*7 -> 6.3 | S106: =H105*10 -> 9
A107: Normativo | B107: Suministro 10 PMU y PDC | C107: Enlasa | D107: Francisco Catalán | E107: 237 | F107: 46203 | G107: Cierre | H107: 0.5 | I107: =E107*H107 -> 118.5 | P107: =I107*10% -> 11.85 | Q107: =I107*15% -> 17.775 | R107: =I107*20% -> 23.7 | T107: =I107*20% -> 23.7
O108: =1.4*H107 -> 0.7 | P108: =H107*2.6 -> 1.3 | R108: =21.5*H107 -> 10.75 | S108: =3.8*H107 -> 1.9 | T108: =H107*43.5 -> 21.75
A109: Scada | B109: Retrofit SCADA | C109: CPP | D109: Francisco Catalán | E109: 94 | F109: 46264 | G109: Cotización | H109: 0 | I109: =E109*H109 -> 0 | R109: =E109*H109*70%*35% -> 0 | S109: =65%*20%*E109*H109 -> 0 | T109: =E109*H109*65%*25% -> 0
R110: =H109*0.3 -> 0 | S110: =R110 -> 0 | T110: =S110 -> 0
N111: =N2+N6+N8+N10+N18+N20+N32+N36+N40+N42+N44+N48+N50+N54+N56+N58+N62+N64+N70+N72+N74+N78+N90+N94+N96 -> 102.8808 | O111: =O2+O6+O8+O10+O18+O20+O32+O36+O40+O42+O44+O48+O50+O54+O56+O58+O62+O64+O70+O72+O74+O78+O90+O94+O96 -> 83.89 | P111: =P2+P6+P8+P10+P18+P20+P32+P36+P40+P42+P44+P48+P50+P54+P56+P58+P62+P64+P70+P72+P74+P78+P90+P94+P96 -> 115.838 | Q111: =Q2+Q6+Q8+Q10+Q18+Q20+Q32+Q36+Q40+Q42+Q44+Q48+Q50+Q54+Q56+Q58+Q62+Q64+Q70+Q72+Q74+Q78+Q90+Q94+Q96 -> 24.3412 | R111: =R2+R6+R8+R10+R18+R20+R32+R36+R40+R42+R44+R48+R50+R54+R56+R58+R62+R64+R70+R72+R74+R78+R90+R94+R96 -> 45.3 | S111: =S2+S6+S8+S10+S18+S20+S32+S36+S40+S42+S44+S48+S50+S54+S56+S58+S62+S64+S70+S72+S74+S78+S90+S94+S96 -> 109.95 | T111: =T2+T6+T8+T10+T18+T20+T32+T36+T40+T42+T44+T48+T50+T54+T56+T58+T62+T64+T70+T72+T74+T78+T90+T94+T96 -> 91.7
N113: =(N105+N107+N109)*1000000 -> 7560000 | O113: =(O105+O107+O109)*1000000 -> 9450000 | P113: =(P105+P107+P109)*1000000 -> 11850000 | Q113: =(Q105+Q107+Q109)*1000000 -> 17775000 | R113: =(R105+R107+R109)*1000000 -> 42600000 | S113: =(S105+S107+S109)*1000000 -> 1890000 | T113: =(T105+T107+T109)*1000000 -> 23700000 | U113: =SUM(N113:T113) -> 1.14825e+08
N114: =(N106+N108+N110)*1000000 -> 0 | O114: =(O106+O108+O110)*1000000 -> 1510000 | P114: =(P106+P108+P110)*1000000 -> 1300000 | Q114: =(Q106+Q108+Q110)*1000000 -> 0 | R114: =(R106+R108+R110)*1000000 -> 17050000 | S114: =(S106+S108+S110)*1000000 -> 10900000 | T114: =(T106+T108+T110)*1000000 -> 21750000 | U114: =SUM(N114:T114) -> 52510000
N116: TOTAL
N117: =N101+N113 -> 110440800 | O117: =O101+O113 -> 93340000 | P117: =P101+P113 -> 1.27688e+08 | Q117: =Q101+Q113 -> 42116200 | R117: =R101+R113 -> 87900000 | S117: =S101+S113 -> 111840000 | T117: =T101+T113 -> 115400000 | U117: =SUM(N117:R117) -> 461485000 | W117: =SUM(N117:S117) -> 573325000
N118: =N102+N114 -> 2030000 | O118: =O102+O114 -> 4420000 | P118: =P102+P114 -> 48050000 | Q118: =Q102+Q114 -> 25630000 | R118: =R102+R114 -> 81060000 | S118: =S102+S114 -> 98270000 | T118: =T102+T114 -> 56390000 | U118: =SUM(N118:S118) -> 259460000 | W118: =SUM(N118:S118) -> 259460000
U119: =U117-U118 -> 202025000 | W119: =W118/W117 -> 0.45255309

Sheet Proyección Q2 (Junio)
A1: Línea | B1: Oportunidad | C1: Cliente | D1: Vendedor | E1: Ingreso esperado | F1: Cierre esperado | G1: Etapa | H1: Probabilidad | I1: Ingreso con % | K1: Resultado Junio | M1: 0 | N1: Agosto | O1: Septiembre | P1: Octubre | Q1: Noviembre | R1: Diciembre | S1: 46388 | T1: 46419
A2: Normativo | B2: Ingeniería 33 PMUs | C2: Colbún | D2: Francisco Catalán | E2: 75 | F2: 46203 | G2: OC | H2: 1 | I2: =E2*H2 -> 75 | K2: OC
A4: Normativo | B4: Integración 2 PMU | C4: ATLAS Renevable Energy | D4: Franco Travaglini | E4: 13 | F4: 46203 | G4: Cierre | H4: 0.7 | I4: =E4*H4 -> 9.1 | K4: Se corre a Julio
A6: Normativo | B6: Implementación 4 PMUs | C6: ENORCHILE S.A. | D6: Bruno Jofré | E6: 122 | F6: 46203 | G6: Cierre 90% (Adjudicación Verbal) | H6: 0.9 | I6: =E6*H6 -> 109.8 | K6: Se corre a Julio | N6: =I6*10% -> 10.98 | O6: =I6*10% -> 10.98 | P6: =I6*15% -> 16.47 | R6: =I6*40% -> 43.92 | S6: =I6*15% -> 16.47 | T6: =I6*10% -> 10.98
O7: =1.6*H6 -> 1.44 | R7: =19.8*H6 -> 17.82 | S7: =34.6*H6 -> 31.14 | T7: =H6*14.6 -> 13.14
A8: Normativo | B8: Implementacion PDC | C8: ENORCHILE S.A. | D8: Bruno Jofré | E8: 70 | F8: 46203 | G8: Cotización | H8: 0.3 | I8: =E8*H8*$M$1 -> 0
A10: Normativo | B10: Suministro Licencias PDC | C10: Minera Escondida Limitada | D10: Bruno Jofré | E10: 5 | F10: 46203 | G10: Cotización | H10: 0.9 | I10: =E10*H10*$M$1 -> 0
A12: Normativo | B12: licencia PDC Corporativo. | C12: REDEIA CORPORACION SA. | D12: Bruno Jofré | E12: 5.5 | F12: 46203 | G12: Cierre | H12: 0.9 | I12: =E12*H12 -> 4.95 | K12: Se corre a Julio
A14: Normativo | B14: Integración PMU Libelula | C14: Engie Energia Chile S.A. | D14: Franco Travaglini | E14: 12 | F14: 46203 | G14: Cierre 90% (Adjudicación Verbal) | H14: 0.9 | I14: =E14*H14 -> 10.8 | K14: Se corre a Julio
A16: Normativo | B16: licencias Firewall | C16: OCCIDENTAL CHEMICAL CHILE LIMITADA | D16: Franco Travaglini | E16: 2 | F16: 46203 | G16: OC | H16: 1 | I16: =E16*H16 -> 2 | K16: OC
A18: Normativo | B18: Asesoria Normativa SITR | C18: C-SES SPA | D18: Franco Travaglini | E18: 5 | F18: 46203 | G18: Cierre 70% (Preferencia) | H18: 0.7 | I18: =E18*H18 -> 3.5 | K18: Se corre a Julio
A20: Normativo | B20: Quantica - Licencias PDC | C20: QUANTICA INGENIERIA SPA | D20: Bruno Jofré | E20: 5 | F20: 46199 | G20: OC | H20: 1 | I20: =E20*H20 -> 5 | K20: Se corre a Sept
A22: Normativo | B22: PMU Domeyko | C22: VERANO EPC SPA | D22: Franco Travaglini | E22: 20 | F22: 46203 | G22: Cierre | H22: 0.5 | I22: =E22*H22 -> 10 | K22: Se corre a Julio
A24: Normativo | B24: SLRP y PDC Centro de Control | C24: Grenergy | D24: Franco Travaglini | E24: 130 | F24: 46203 | G24: Cierre 90% (Adjudicación Verbal) | H24: 0.9 | I24: =E24*H24 -> 117 | K24: Se corre a Agosto | N24: =I24/5 -> 23.4 | O24: =#REF! -> #REF! | P24: =#REF! -> #REF! | Q24: =#REF! -> #REF! | R24: =#REF! -> #REF!
A26: Normativo | B26: Mtto PDCE 2026 | C26: TRANSELEC S A | D26: Franco Travaglini | E26: 50 | F26: 46203 | G26: Cotización | H26: 0.7 | I26: =E26*H26*$M$1 -> 0 | O26: =I26/2 -> 0 | R26: =O26 -> 0
A28: Normativo | B28: LICENCIAS PDC Corportivo x 2 | C28: WPD Chile | D28: Francisco Catalan | E28: 4 | F28: 46203 | G28: Posicionamiento | H28: 0.3 | I28: =E28*H28*$M$1 -> 0 | P28: =E28*H28*20% -> 0.24 | Q28: =E28*H28*25% -> 0.3 | T28: =E28*H28*50% -> 0.6
A30: Normativo | B30: SITR Linea 7 | C30: EMPRESA DE TRANSPORTES DE PASAJEROS METRO S.A. | D30: Franco Travaglini | E30: 22 | F30: 46203 | G30: Cierre 70% (Preferencia) | H30: 0.5 | I30: =E30*H30 -> 11 | K30: Se corre al 2027
A32: Normativo | B32: Vertice - Suministro GPS para EDAC ENAEX | C32: VERTICE CONSULTORES SPA | D32: Bruno Jofré | E32: 7 | F32: 46203 | G32: Posicionamiento | H32: 0.6 | I32: =E32*H32*$M$1 -> 0
A34: Normativo | B34: PMU Mantos Blancos | C34: Mantos Cooper | D34: Francisco Catalan | E34: 35 | F34: 46203 | G34: Cotización | H34: 0.5 | I34: =E34*H34*$M$1 -> 0
A36: PAC | B36: TEN - Suministro 2 RTU Orion + Configuración | C36: Transmisora Electrica Del Norte S.A. | D36: Kevin Fuentealba | E36: 30 | F36: 46203 | G36: Cierre | H36: 0.1 | I36: =E36*H36 -> 3 | K36: Se corre a Octubre
A38: PAC | B38: Suministro RTU Codelco | C38: Vertice consultores | D38: Kevin Fuentealba | E38: 4 | F38: 46199 | G38: Cierre | H38: 0.25 | I38: =E38*H38 -> 1 | K38: Se corre a Agosto
A40: PAC | B40: Piloto de integración Medidores | C40: AES ANDES S.A. | D40: Franco Travaglini | E40: 3 | F40: 46203 | G40: Posicionamiento | H40: 0.25 | I40: =E40*H40*$M$1 -> 0
A42: PAC | B42: Tecnored - Actualización EDAC y Reemplazo RTU Inchalam | C42: Tecnored S.A. | D42: Kevin Fuentealba | E42: 41 | F42: 46199 | G42: Cierre | H42: 0.15 | I42: =E42*H42 -> 6.15 | K42: Fuera del embudo
A44: PAC | B44: Servicios Reconectadores Fase 1 | C44: Chilquinta Distribucion S.A. | D44: Kevin Fuentealba | E44: 40 | F44: 46203 | G44: OC | H44: 1 | I44: =E44*H44 -> 40 | K44: OC
A46: SCADA | B46: Servicio arriendo de maleta omicron 356 - Synchroteq | C46: Engie Energia Chile S.A. | D46: Kevin Fuentealba | E46: 2 | F46: 46203 | G46: OC | H46: 1 | I46: =E46*H46 -> 2 | K46: OC
A48: PAC | B48: Servicio de Independización de Nucleos | C48: Engie Energia Chile S.A. | D48: Kevin Fuentealba | E48: 7 | F48: 46203 | G48: OC | H48: 1 | I48: =E48*H48 -> 7 | K48: OC
A50: Normativo | B50: Eletrans Implementación 2 x PMU | C50: Eletrans III S.A | D50: Bruno Jofré | E50: 66 | F50: 46171 | G50: OC | H50: 1 | I50: =E50*H50 -> 66 | K50: OC | O50: =E50*H50*20% -> 13.2 | P50: =E50*H50*25% -> 16.5 | S50: =E50*H50*50% -> 33
I51: l | N51: =H50*1.5 -> 1.5 | Q51: =H50*2.5 -> 2.5 | R51: =H50*1.4 -> 1.4 | S51: =H50*23 -> 23
A52: Normativo | B52: Suministro Gabinetes para PMU | C52: CGE TRANSMISION SA | D52: Bruno Jofré | E52: 9 | F52: 46171 | G52: OC | H52: 1 | I52: =E52*H52 -> 9 | K52: OC
G56: PROYECCIÓN ACTUALIZADA AL CIERRE DE MAYO | H56: Abril | I56: ='Proyección Q2 (Abril)'!I133 -> 437 | J56: =Panel!F119 -> 79.454 | K56: =J56-I56 -> -357.546 | N56: =(#REF!+#REF!+#REF!+#REF!+#REF!+N50+N79+#REF!+#REF!+N81+N83+#REF!+#REF!+#REF!+#REF!+#REF!+#REF!+#REF!+#REF!+#REF!+#REF!+#REF!+#REF!+#REF!+#REF!)*1000000 -> #REF! | O56: =(#REF!+#REF!+#REF!+#REF!+#REF!+O50+O79+#REF!+#REF!+O81+O83+#REF!+#REF!+#REF!+#REF!+#REF!+#REF!+#REF!+#REF!+#REF!+#REF!+#REF!+#REF!+#REF!+#REF!)*1000000 -> #REF! | P56: =(#REF!+#REF!+#REF!+#REF!+#REF!+P50+P79+#REF!+#REF!+P81+P83+#REF!+#REF!+#REF!+#REF!+#REF!+#REF!+#REF!+#REF!+#REF!+#REF!+#REF!+#REF!+#REF!+#REF!)*1000000 -> #REF! | Q56: =(#REF!+#REF!+#REF!+#REF!+#REF!+Q50+Q79+#REF!+#REF!+Q81+Q83+#REF!+#REF!+#REF!+#REF!+#REF!+#REF!+#REF!+#REF!+#REF!+#REF!+#REF!+#REF!+#REF!+#REF!)*1000000 -> #REF! | R56: =(#REF!+#REF!+#REF!+#REF!+#REF!+R50+R79+#REF!+#REF!+R81+R83+#REF!+#REF!+#REF!+#REF!+#REF!+#REF!+#REF!+#REF!+#REF!+#REF!+#REF!+#REF!+#REF!+#REF!)*1000000 -> #REF! | S56: =(#REF!+#REF!+#REF!+#REF!+#REF!+S50+S79+#REF!+#REF!+S81+S83+#REF!+#REF!+#REF!+#REF!+#REF!+#REF!+#REF!+#REF!+#REF!+#REF!+#REF!+#REF!+#REF!+#REF!)*1000000 -> #REF! | T56: =(#REF!+#REF!+#REF!+#REF!+#REF!+T50+T79+#REF!+#REF!+T81+T83+#REF!+#REF!+#REF!+#REF!+#REF!+#REF!+#REF!+#REF!+#REF!+#REF!+#REF!+#REF!+#REF!+#REF!)*1000000 -> #REF! | U56: =SUM(N56:T56) -> #REF!
H57: Mayo | I57: =SUM(I46:I83) -> 132.1 | J57: =Panel!F136 -> 535.824 | K57: =J57-I57 -> 354.11 | N57: =(#REF!+#REF!+#REF!+#REF!+#REF!+N51+N80+#REF!+#REF!+N82+N84+#REF!+#REF!+#REF!+#REF!+#REF!+#REF!+#REF!+#REF!+#REF!+#REF!+#REF!+#REF!+#REF!+#REF!)*1000000 -> #REF! | O57: =(#REF!+#REF!+#REF!+#REF!+#REF!+O51+O80+#REF!+#REF!+O82+O84+#REF!+#REF!+#REF!+#REF!+#REF!+#REF!+#REF!+#REF!+#REF!+#REF!+#REF!+#REF!+#REF!+#REF!)*1000000 -> #REF! | P57: =(#REF!+#REF!+#REF!+#REF!+#REF!+P51+P80+#REF!+#REF!+P82+P84+#REF!+#REF!+#REF!+#REF!+#REF!+#REF!+#REF!+#REF!+#REF!+#REF!+#REF!+#REF!+#REF!+#REF!)*1000000 -> #REF! | Q57: =(#REF!+#REF!+#REF!+#REF!+#REF!+Q51+Q80+#REF!+#REF!+Q82+Q84+#REF!+#REF!+#REF!+#REF!+#REF!+#REF!+#REF!+#REF!+#REF!+#REF!+#REF!+#REF!+#REF!+#REF!)*1000000 -> #REF! | R57: =(#REF!+#REF!+#REF!+#REF!+#REF!+R51+R80+#REF!+#REF!+R82+R84+#REF!+#REF!+#REF!+#REF!+#REF!+#REF!+#REF!+#REF!+#REF!+#REF!+#REF!+#REF!+#REF!+#REF!)*1000000 -> #REF! | S57: =(#REF!+#REF!+#REF!+#REF!+#REF!+S51+S80+#REF!+#REF!+S82+S84+#REF!+#REF!+#REF!+#REF!+#REF!+#REF!+#REF!+#REF!+#REF!+#REF!+#REF!+#REF!+#REF!+#REF!)*1000000 -> #REF! | T57: =(#REF!+#REF!+#REF!+#REF!+#REF!+T51+T80+#REF!+#REF!+T82+T84+#REF!+#REF!+#REF!+#REF!+#REF!+#REF!+#REF!+#REF!+#REF!+#REF!+#REF!+#REF!+#REF!+#REF!)*1000000 -> #REF! | U57: =SUM(N57:T57) -> #REF!
H58: Junio | I58: =SUM(I2:I52) -> 492.3 | J58: =Panel!F150 -> 237.777 | K58: =J58-I58 -> -254.523
A60: Normativo | B60: PMU | C60: Barrick | D60: Bruno Jofré | E60: 42 | F60: Mayo | G60: Cierre | H60: 0.9 | I60: =E60*H60 -> 37.8 | N60: =I60*20% -> 7.56 | O60: =I60*25% -> 9.45 | R60: =I60*50% -> 18.9 | S60: =I60*5% -> 1.89
O61: =0.9*H60 -> 0.81 | R61: =H60*7 -> 6.3 | S61: =H60*10 -> 9
A62: Normativo | B62: Suministro 10 PMU y PDC | C62: Enlasa | D62: Francisco Catalán | E62: 237 | F62: 46203 | G62: Cierre | H62: 0.5 | I62: =E62*H62 -> 118.5 | P62: =I62*10% -> 11.85 | Q62: =I62*15% -> 17.775 | R62: =I62*20% -> 23.7 | T62: =I62*20% -> 23.7
O63: =1.4*H62 -> 0.7 | P63: =H62*2.6 -> 1.3 | R63: =21.5*H62 -> 10.75 | S63: =3.8*H62 -> 1.9 | T63: =H62*43.5 -> 21.75
A64: Scada | B64: Retrofit SCADA | C64: CPP | D64: Francisco Catalán | E64: 94 | F64: 46264 | G64: Cotización | H64: 0 | I64: =E64*H64 -> 0 | R64: =E64*H64*70%*35% -> 0 | S64: =65%*20%*E64*H64 -> 0 | T64: =E64*H64*65%*25% -> 0
R65: =H64*0.3 -> 0 | S65: =R65 -> 0 | T65: =S65 -> 0
N66: =#REF!+#REF!+#REF!+#REF!+#REF!+N50+N79+#REF!+#REF!+N81+N83+#REF!+#REF!+#REF!+#REF!+#REF!+#REF!+#REF!+#REF!+#REF!+#REF!+#REF!+#REF!+#REF!+#REF! -> #REF! | O66: =#REF!+#REF!+#REF!+#REF!+#REF!+O50+O79+#REF!+#REF!+O81+O83+#REF!+#REF!+#REF!+#REF!+#REF!+#REF!+#REF!+#REF!+#REF!+#REF!+#REF!+#REF!+#REF!+#REF! -> #REF! | P66: =#REF!+#REF!+#REF!+#REF!+#REF!+P50+P79+#REF!+#REF!+P81+P83+#REF!+#REF!+#REF!+#REF!+#REF!+#REF!+#REF!+#REF!+#REF!+#REF!+#REF!+#REF!+#REF!+#REF! -> #REF! | Q66: =#REF!+#REF!+#REF!+#REF!+#REF!+Q50+Q79+#REF!+#REF!+Q81+Q83+#REF!+#REF!+#REF!+#REF!+#REF!+#REF!+#REF!+#REF!+#REF!+#REF!+#REF!+#REF!+#REF!+#REF! -> #REF! | R66: =#REF!+#REF!+#REF!+#REF!+#REF!+R50+R79+#REF!+#REF!+R81+R83+#REF!+#REF!+#REF!+#REF!+#REF!+#REF!+#REF!+#REF!+#REF!+#REF!+#REF!+#REF!+#REF!+#REF! -> #REF! | S66: =#REF!+#REF!+#REF!+#REF!+#REF!+S50+S79+#REF!+#REF!+S81+S83+#REF!+#REF!+#REF!+#REF!+#REF!+#REF!+#REF!+#REF!+#REF!+#REF!+#REF!+#REF!+#REF!+#REF! -> #REF! | T66: =#REF!+#REF!+#REF!+#REF!+#REF!+T50+T79+#REF!+#REF!+T81+T83+#REF!+#REF!+#REF!+#REF!+#REF!+#REF!+#REF!+#REF!+#REF!+#REF!+#REF!+#REF!+#REF!+#REF! -> #REF!
N68: =(N60+N62+N64)*1000000 -> 7560000 | O68: =(O60+O62+O64)*1000000 -> 9450000 | P68: =(P60+P62+P64)*1000000 -> 11850000 | Q68: =(Q60+Q62+Q64)*1000000 -> 17775000 | R68: =(R60+R62+R64)*1000000 -> 42600000 | S68: =(S60+S62+S64)*1000000 -> 1890000 | T68: =(T60+T62+T64)*1000000 -> 23700000 | U68: =SUM(N68:T68) -> 1.14825e+08
N69: =(N61+N63+N65)*1000000 -> 0 | O69: =(O61+O63+O65)*1000000 -> 1510000 | P69: =(P61+P63+P65)*1000000 -> 1300000 | Q69: =(Q61+Q63+Q65)*1000000 -> 0 | R69: =(R61+R63+R65)*1000000 -> 17050000 | S69: =(S61+S63+S65)*1000000 -> 10900000 | T69: =(T61+T63+T65)*1000000 -> 21750000 | U69: =SUM(N69:T69) -> 52510000
N71: TOTAL
N72: =N56+N68 -> #REF! | O72: =O56+O68 -> #REF! | P72: =P56+P68 -> #REF! | Q72: =Q56+Q68 -> #REF! | R72: =R56+R68 -> #REF! | S72: =S56+S68 -> #REF! | T72: =T56+T68 -> #REF! | U72: =SUM(N72:R72) -> #REF! | W72: =SUM(N72:S72) -> #REF!
N73: =N57+N69 -> #REF! | O73: =O57+O69 -> #REF! | P73: =P57+P69 -> #REF! | Q73: =Q57+Q69 -> #REF! | R73: =R57+R69 -> #REF! | S73: =S57+S69 -> #REF! | T73: =T57+T69 -> #REF! | U73: =SUM(N73:S73) -> #REF! | W73: =SUM(N73:S73) -> #REF!
U74: =U72-U73 -> #REF! | W74: =W73/W72 -> #REF!
A77: Normativo | B77: 2 PMU | C77: Consorcio Santa Marta S.A. | D77: Francisco Catalan | E77: 55 | F77: 46157 | G77: Cierre | H77: 0.1 | I77: =E77*H77 -> 5.5 | K77: Se corre a Agosto | N77: =I77*20% -> 1.1 | O77: =I77*10% -> 0.55 | P77: =I77*20% -> 1.1 | Q77: =I77*25% -> 1.375 | R77: =I77*20% -> 1.1 | S77: =I77*5% -> 0.275
O78: =0.1*H77 -> 0.01 | Q78: =2.3*H77 -> 0.23 | R78: =H77*10 -> 1 | S78: =H77*6.2 -> 0.62
A79: Normativo | B79: PMU Zona Centro | C79: TRANSELEC S A | D79: Franco Travaglini | E79: 160 | F79: JULIO | G79: Cierre | H79: 0.7 | I79: =E79*H79 -> 112 | J79: Actualizar flujo 260317 | O79: =I79*10% -> 11.2 | S79: =60%*I79 -> 67.2 | T79: =I79*30% -> 33.6
I80: l | N80: =1.4*H79 -> 0.98 | O80: =0.3*H79 -> 0.21 | R80: =9.2*H79 -> 6.44 | S80: =1.1*H79 -> 0.77 | T80: =17*H79 -> 11.9
A81: Normativo | B81: implementación 18 x PMU | C81: Grupo Saesa | D81: Franco Travaglini | E81: 300 | F81: 46172 | G81: Cierre 60% (CT Cubierto) | H81: 0.7 | I81: =E81*H81 -> 210 | N81: =I81*20% -> 42 | O81: =I81*10% -> 21 | P81: =I81*15% -> 31.5 | Q81: =I81*5% -> 10.5 | T81: =I81*21% -> 44.1 | U81: =I81*9% -> 18.9 | V81: =I81*20% -> 42
I82: l | O82: =1*H81 -> 0.7 | Q82: =9.9*H81 -> 6.93 | R82: =20*H81 -> 14 | S82: =76*H81 -> 53.2 | T82: =4.2*H81 -> 2.94 | U82: =4*H81 -> 2.8 | W82: =44*H81 -> 30.8
A83: SCADA | B83: SCADA Nova - CC | C83: ENAP | D83: Franco Travaglini | E83: 118 | F83: 46172 | G83: Cierre | H83: 0.5 | I83: =E83*H83 -> 59 | N83: =I83/5 -> 11.8 | O83: =$N$83 -> 11.8 | P83: =$N$83 -> 11.8 | Q83: =$N$83 -> 11.8 | R83: =$N$83 -> 11.8
I84: l | O84: =2.4*H83 -> 1.2 | P84: =8.5*H83 -> 4.25 | Q84: =H83*33 -> 16.5 | R84: =H83*4.9 -> 2.45

Sheet Proyección Q3 (Julio)
A1: Línea | B1: Oportunidad | C1: Cliente | D1: Vendedor | E1: Ingreso esperado | F1: Cierre esperado | G1: Etapa | H1: Probabilidad | I1: Ingreso con % | K1: Resultado Julio | L1: 0 | M1: Agosto | N1: Septiembre | O1: Octubre | P1: Noviembre | Q1: Diciembre | R1: 46388 | S1: 46419 | T1: 46447 | U1: 46478 | V1: 46508 | W1: 46539 | X1: 46569
A2: Normativo | B2: PMU Domeyko | C2: VERANO EPC SPA | D2: Bruno Jofré | E2: 32 | F2: 46213 | G2: Cierre 90% (Adjudicación Verbal) | H2: 1 | I2: =E2*H2 -> 32 | N2: =I2*10% -> 3.2 | O2: =I2*10% -> 3.2 | R2: =I2*30% -> 9.6 | S2: =I2*50% -> 16
O3: =H2*0.4 -> 0.4 | Q3: =1.6*H2 -> 1.6 | R3: =4.9*H2 -> 4.9 | S3: =5.3*H2 -> 5.3 | T3: =H2*1.7 -> 1.7
A4: Normativo | B4: licencia PDC Corporativo. | C4: REDEIA CORPORACION SA. | D4: Bruno Jofré | E4: 5.5 | F4: 46213 | G4: Cierre | H4: 1 | I4: =E4*H4 -> 5.5 | N4: =I4 -> 5.5
O5: =I4*0.85 -> 4.675
A6: Normativo | B6: Pruebas PRS-SCADA | C6: Enfragen , Llc | D6: Francisco Catalan | E6: 28 | F6: 46227 | G6: Cierre 90% (Adjudicación Verbal) | H6: 1 | I6: =E6*H6 -> 28
A8: Normativo | B8: Implementación 4 PMUs | C8: ENORCHILE S.A. | D8: Bruno Jofré | E8: 102 | F8: 46234 | G8: Cierre 90% (Adjudicación Verbal) | H8: 0.9 | I8: =E8*H8 -> 91.8 | N8: =I8*10% -> 9.18 | O8: =I8*10% -> 9.18 | P8: =I8*15% -> 13.77 | R8: =I8*40% -> 36.72 | S8: =I8*15% -> 13.77 | T8: =I8*10% -> 9.18
O9: =H8*1.5 -> 1.35 | R9: =4.5*H8 -> 4.05 | S9: =30*H8 -> 27 | T9: =H8*14 -> 12.6
A10: Normativo | B10: Pruebas PRS | C10: SAESA | D10: Francisco Catalan | E10: 20 | F10: 46234 | G10: Cotización | H10: 0.5 | I10: =E10*H10*$L$1 -> 0
A12: Normativo | B12: Integración 2 PMU a PDC | C12: Acciona Energia Chile S.p.A. | D12: Franco Travaglini | E12: 14 | F12: 46234 | G12: Cierre | H12: 0.5 | I12: =E12*H12 -> 7 | J12: No tiene flujo
A14: Normativo | B14: Integración PMU Libelula | C14: Engie Energia Chile S.A. | D14: Franco Travaglini | E14: 12 | F14: 46234 | G14: Cierre 90% (Adjudicación Verbal) | H14: 0.9 | I14: =E14*H14 -> 10.8 | J14: No tiene flujo
A16: Normativo | B16: Asesoria Normativa SITR | C16: C-SES SPA | D16: Franco Travaglini | E16: 5 | F16: 46234 | G16: Cierre 70% (Preferencia) | H16: 0.7 | I16: =E16*H16 -> 3.5 | J16: No tiene flujo
A18: Normativo | B18: Implementación 7 PMU | C18: Electrica Puntilla | D18: Francisco Catalan | E18: 190 | F18: 46234 | G18: Cierre 70% (Preferencia) | H18: 0.9 | I18: =E18*H18 -> 171 | J18: Falta flujo
A20: Normativo | B20: PMU Zona Centro | C20: TRANSELEC S A | D20: Franco Travaglini | E20: 160 | F20: 46234 | G20: Cierre | H20: 0.7 | I20: =E20*H20 -> 112 | N20: =I20*10% -> 11.2 | S20: =I20*60% -> 67.2 | T20: =I20*30% -> 33.6
M21: =H20*1.4 -> 0.98 | N21: =H20*0.3 -> 0.21 | Q21: =H20*9.2 -> 6.44 | R21: =H20*1.1 -> 0.77 | S21: =H20*18 -> 12.6
A22: Normativo | B22: Integración PMU Arrayan a Maitencillo | C22: Sonnedix Chile Holding S.p.A. | D22: Bruno Jofré | E22: 8 | F22: 46234 | G22: Cierre | H22: 0.3 | I22: =E22*H22 -> 2.4
A24: PAC | B24: Servicios Protecciones | C24: Transquinta | D24: Kevin Fuentealba | E24: 10 | F24: 46234 | G24: Cierre | H24: 0.6 | I24: =E24*H24 -> 6
A26: PAC | B26: Servicios Protecciones | C26: CTNG | D26: Kevin Fuentealba | E26: 6 | F26: 46234 | G26: Cierre | H26: 0.6 | I26: =E26*H26 -> 3.6
A28: PAC | B28: Servicios Protecciones | C28: Eletrans III | D28: Kevin Fuentealba | E28: 8 | F28: 46234 | G28: Cierre | H28: 0.6 | I28: =E28*H28 -> 4.8
A30: PAC | B30: Servicios Protecciones | C30: Eletrans I | D30: Kevin Fuentealba | E30: 13 | F30: 46234 | G30: Cierre | H30: 0.6 | I30: =E30*H30 -> 7.8
A32: PAC | B32: Servicios Protecciones | C32: Transquinta | D32: Kevin Fuentealba | E32: 3 | F32: 46234 | G32: Cierre | H32: 0.6 | I32: =E32*H32 -> 1.8
A34: SCADA | B34: Contrato de mantenimiento | C34: Cementos Melon | D34: Francisco Catalan | E34: 31 | F34: 46234 | G34: Cierre 90% (Adjudicación Verbal) | H34: 0.7 | I34: =E34*H34 -> 21.7 | M34: =$I$34/24 -> 0.90416667 | N34: =$I$34/24 -> 0.90416667 | O34: =$I$34/24 -> 0.90416667 | P34: =$I$34/24 -> 0.90416667 | Q34: =$I$34/24 -> 0.90416667 | R34: =$I$34/24 -> 0.90416667 | S34: =$I$34/24 -> 0.90416667 | T34: =$I$34/24 -> 0.90416667 | ... X34: =$I$34/24 -> 0.90416667
A36: SCADA | B36: Estación de Ingeniería | C36: Gestion de Proyectos Electricos S.A. | D36: Franco Travaglini | E36: 8 | F36: 46234 | G36: Cierre | H36: 0.7 | I36: =E36*H36 -> 5.6 | J36: No tiene flujo
A38: SCADA | B38: Licencia SQL | C38: Cooperativa Regional Electrica Llanquihue Limitada | D38: Franco Travaglini | E38: 1 | F38: 46234 | G38: Cierre | H38: 1 | I38: =E38*H38 -> 1 | J38: No tiene flujo
A40: SCADA | B40: Retrofit Lomas Bayas | C40: Lomas Bayas | D40: Francisco Catalan | E40: 158 | F40: 46234 | G40: Cierre | H40: 0.3 | I40: =E40*H40 -> 47.4 | J40: Flujo
A42: Normativo | B42: Implementación 2 PMUs | C42: X-elio | D42: Bruno Jofré | E42: 60 | F42: 46262 | G42: Cierre 60% (CT Cubierto) | H42: 0.3 | I42: =E42*H42 -> 18
A44: Normativo | B44: SLRP y PDC Centro de Control | C44: Grenergy | D44: Franco Travaglini | E44: 130 | F44: 46262 | G44: Cierre 90% (Adjudicación Verbal) | H44: 0.9 | I44: =E44*H44 -> 117 | J44: Flujo
A46: PAC | B46: Retrofit de RTU SE Polpaico | C46: TRANSELEC S A | D46: Kevin Fuentealba | E46: 150 | F46: 46262 | G46: Cierre | H46: 0.3 | I46: =E46*H46 -> 45 | O46: =I46*72%*15% -> 4.86 | Q46: =I46*72%*15% -> 4.86 | R46: =I46*72%*20% -> 6.48 | V46: =I46*72%*25% -> 8.1 | W46: =I46*72%*10% -> 3.24 | X46: =I46*72%*10% -> 3.24 | Y46: =I46*72%*10% -> 3.24
O47: =H46*4.1 -> 1.23 | S47: =H46*7 -> 2.1 | T47: =H46*4.5 -> 1.35 | U47: =H46*35.1 -> 10.53 | V47: =H46*10.8 -> 3.24 | W47: =H46*3.5 -> 1.05 | X47: =H46*23 -> 6.9 | Y47: =H46*2.6 -> 0.78 | Z47: =H46*3.5 -> 1.05
A48: PAC | B48: Guacolda - Eficiencia Energetica (Medidores) | C48: Guacolda Energia SpA | D48: Kevin Fuentealba | E48: 55 | F48: 46262 | G48: Cierre | H48: 0.25 | I48: =E48*H48 -> 13.75
A50: PAC | B50: CMP - Mina El Romeral - Implementación RTU / SCADA Local | C50: Compania Minera del Pacifico S.A. | D50: Kevin Fuentealba | E50: 60 | F50: 46262 | G50: Cotización | H50: 0.3 | I50: =E50*H50*$L$1 -> 0
A52: Normativo | B52: implementación 18 x PMU | C52: Grupo Saesa | D52: Franco Travaglini | E52: 300 | F52: 46265 | G52: Cierre | H52: 0.3 | I52: =E52*H52 -> 90 | O52: =I52*20% -> 18 | P52: =I52*10% -> 9 | Q52: =I52*15% -> 13.5 | R52: =I52*5% -> 4.5 | U52: =I52*21% -> 18.9 | V52: =I52*9% -> 8.1 | W52: =I52*20% -> 18
P53: =H52*1 -> 0.3 | R53: =H52*10 -> 3 | S53: =H52*20 -> 6 | T53: =H52*76 -> 22.8 | U53: =H52*4.2 -> 1.26 | V53: =H52*4 -> 1.2 | X53: =H52*44 -> 13.2
A54: Normativo | B54: Licencias PDC LOCAL Y CORPO | C54: Colbun S.A. | D54: Francisco Catalan | E54: 220 | F54: 46265 | G54: Cotización | H54: 0.3 | I54: =E54*H54*$L$1 -> 0
A56: Normativo | B56: Suministro Licencias PDC | C56: Minera Escondida Limitada | D56: Bruno Jofré | E56: 5 | F56: 46265 | G56: Cierre | H56: 0.9 | I56: =E56*H56 -> 4.5
A58: Normativo | B58: Sonnedix Integración 7 PMU | C58: Sonnedix | D58: Franco Travaglini | E58: 50 | F58: 46265 | G58: Cierre | H58: 0.5 | I58: =E58*H58 -> 25 | O58: =I58*23%*15%+I58*37%*20% -> 2.7125 | P58: =I58*23%*25%+I58*25% -> 7.6875 | Q58: =I58*23%*40%+I58*37%*80%+I58*14% -> 13.2 | R58: =I58*23%*15% -> 0.8625 | S58: =I58*23%*5% -> 0.2875
R59: =H58*28.5 -> 14.25 | S59: =H58*15 -> 7.5
A60: Normativo | B60: Suministro e implementación 2 PMU | C60: Consorcio Santa Marta S.A. | D60: Francisco Catalan | E60: 55 | F60: 46265 | G60: Cierre | H60: 0.1 | I60: =E60*H60 -> 5.5
A62: Normativo | B62: Mtto PDCE 2026 | C62: TRANSELEC S A | D62: Franco Travaglini | E62: 50 | F62: 46265 | G62: Cierre | H62: 0.7 | I62: =E62*H62 -> 35 | O62: =I62*50% -> 17.5
A64: Normativo | B64: Prime Energía 21 PMU y PDC | C64: Enfragen , Llc | D64: Franco Travaglini | E64: 480 | F64: 46265 | G64: Cierre | H64: 0.3 | I64: =E64*H64 -> 144 | O64: =I64*45%*25%+I64*55%*30% -> 39.96 | R64: =I64*45%*15%+I64*55%*50% -> 49.32 | S64: =I64*45%*20% -> 12.96 | W64: =I64*45%*25% -> 16.2 | AA64: =I64*45%*10%+I64*55%*20% -> 22.32 | AB64: =I64*45%*5% -> 3.24
O65: =H64*5.3 -> 1.59 | P65: =H64*5.3 -> 1.59 | Q65: =H64*5.3 -> 1.59 | T65: =H64*7.5 -> 2.25 | U65: =H64*92 -> 27.6 | V65: =H64*23.4 -> 7.02 | W65: =H64*67.4 -> 20.22 | X65: =H64*66.3 -> 19.89 | Y65: =H64*26.2 -> 7.86 | Z65: =H64*26.2 -> 7.86 | AA65: =H64*65 -> 19.5
A66: Normativo | B66: PMU Mantos Blancos | C66: Mantos Cooper | D66: Francisco Catalan | E66: 35 | F66: 46265 | G66: Cotización | H66: 0.3 | I66: =E66*H66*$L$1 -> 0
A68: SCADA | B68: SCADA Nova - CC | C68: ENAP | D68: Franco Travaglini | E68: 118 | F68: 46265 | G68: Cierre | H68: 0.5 | I68: =E68*H68 -> 59 | J68: Flujo
A70: PAC | B70: Retrofit RTU SE Reñaca | C70: Chilquinta Transmisión S.A. | D70: Kevin Fuentealba | E70: 50 | F70: 46265 | G70: Cierre 60% (CT Cubierto) | H70: 0.6 | I70: =E70*H70 -> 30
A72: PAC | B72: RTU - SE Laberinto | C72: Chilquinta Transmisión S.A. | D72: Kevin Fuentealba | E72: 80 | F72: 46265 | G72: Cierre 60% (CT Cubierto) | H72: 0.6 | I72: =E72*H72 -> 48 | O72: =I72*70%*20% -> 6.72 | P72: =I72*70%*20%+I72*30% -> 21.12 | Q72: =I72*70%*20% -> 6.72 | R72: =I72*70%*15% -> 5.04 | S72: =I72*70%*15% -> 5.04 | T72: =I72*70%*10% -> 3.36
P73: =H72*1 -> 0.6 | R73: =H72*17 -> 10.2 | S73: =H72*4.5 -> 2.7
A74: PAC | B74: Chilquinta - Retrofit de RTU S/E Quilpue | C74: Chilquinta Transmisión S.A. | D74: Kevin Fuentealba | E74: 60 | F74: 46265 | G74: Cierre 60% (CT Cubierto) | H74: 0.6 | I74: =E74*H74 -> 36 | O74: =I74*46%*20% -> 3.312 | P74: =I74*46%*20%+I74*54% -> 22.752 | Q74: =I74*46%*20% -> 3.312 | R74: =I74*46%*15% -> 2.484 | S74: =I74*46%*20% -> 3.312 | T74: =I74*46%*5% -> 0.828
P75: =H74*0.7 -> 0.42 | R75: =H74*42 -> 25.2 | S75: =H74*3 -> 1.8
A76: PAC | B76: Servicios RTU SE Balandras | C76: Chilquinta Transmisión S.A. | D76: Kevin Fuentealba | E76: 20 | F76: 46265 | G76: Cierre 90% (Adjudicación Verbal) | H76: 0.9 | I76: =E76*H76 -> 18
A78: PAC | B78: Suministro RTU Codelco | C78: Vertice consultores | D78: Kevin Fuentealba | E78: 4 | F78: 46265 | G78: Cierre | H78: 0.25 | I78: =E78*H78 -> 1
A80: Normativo | B80: Suministro e Integración 4 x PMU y 1 x PDC centralizado | C80: Statkraft | D80: Francisco Catalan | E80: 145 | F80: 46295 | G80: Cierre | H80: 0.5 | I80: =E80*H80 -> 72.5 | J80: Flujo
A82: Normativo | B82: Auditoria SDAC | C82: Coordinador Independiente del Sistema Electrico Nacional | D82: Franco Travaglini | E82: 120 | F82: 46295 | G82: Cierre | H82: 0.3 | I82: =E82*H82 -> 36 | P82: =$I$82/6 -> 6 | Q82: =$I$82/6 -> 6 | R82: =$I$82/6 -> 6 | S82: =$I$82/6 -> 6 | T82: =$I$82/6 -> 6 | U82: =$I$82/6 -> 6
A84: Normativo | B84: Quantica - Licencias PDC | C84: QUANTICA INGENIERIA SPA | D84: Bruno Jofré | E84: 5 | F84: 46295 | G84: Cierre 70% (Preferencia) | H84: 0.7 | I84: =E84*H84 -> 3.5
A86: SCADA | B86: Visualización Móvil | C86: Gestion de Proyectos Electricos S.A. | D86: Franco Travaglini | E86: 35 | F86: 46295 | G86: Cierre | H86: 0.5 | I86: =E86*H86 -> 17.5
A88: PAC | B88: Chilquinta Zona Cordillera - Retrofit de 5 RTU | C88: Chilquinta Transmisión S.A. | D88: Kevin Fuentealba | E88: 250 | F88: 46295 | G88: Cotización | H88: 0.3 | I88: =E88*H88*$L$1 -> 0
A90: PAC | B90: Retrofit Protecciones La Huayca | C90: Enlight Investments Spa | D90: Kevin Fuentealba | E90: 100 | F90: 46295 | G90: Cierre | H90: 0.3 | I90: =E90*H90 -> 30 | P90: =I90*20% -> 6 | Q90: =I90*20% -> 6 | R90: =I90*20% -> 6 | S90: =I90*30% -> 9 | T90: =I90*10% -> 3
Q91: =H90*3.2 -> 0.96 | R91: =H90*3.2 -> 0.96 | S91: =H90*8 -> 2.4
G94: PROYECCIÓN ACTUALIZADA AL CIERRE DE JUNIO | H94: Julio | I94: =SUM(I2:I40) -> 563.7 | M94: =M2+M4+M6+M8+M10+M12+M14+M16+M18+M20+M22+M24+M26+M28+M30+M32+M34+M36+M38+M40+M42+M44+M46+M48+M50+M52+M54+M56+M58+M60+M62+M64+M66+M68+M70+M72+M74+M76+M78+M80+M82+M84+M86+M88+M90 -> 0.90416667 | N94: =N2+N4+N6+N8+N10+N12+N14+N16+N18+N20+N22+N24+N26+N28+N30+N32+N34+N36+N38+N40+N42+N44+N46+N48+N50+N52+N54+N56+N58+N60+N62+N64+N66+N68+N70+N72+N74+N76+N78+N80+N82+N84+N86+N88+N90 -> 29.984167 | O94: =O2+O4+O6+O8+O10+O12+O14+O16+O18+O20+O22+O24+O26+O28+O30+O32+O34+O36+O38+O40+O42+O44+O46+O48+O50+O52+O54+O56+O58+O60+O62+O64+O66+O68+O70+O72+O74+O76+O78+O80+O82+O84+O86+O88+O90 -> 106.34867 | P94: =P2+P4+P6+P8+P10+P12+P14+P16+P18+P20+P22+P24+P26+P28+P30+P32+P34+P36+P38+P40+P42+P44+P46+P48+P50+P52+P54+P56+P58+P60+P62+P64+P66+P68+P70+P72+P74+P76+P78+P80+P82+P84+P86+P88+P90 -> 87.233667 | Q94: =Q2+Q4+Q6+Q8+Q10+Q12+Q14+Q16+Q18+Q20+Q22+Q24+Q26+Q28+Q30+Q32+Q34+Q36+Q38+Q40+Q42+Q44+Q46+Q48+Q50+Q52+Q54+Q56+Q58+Q60+Q62+Q64+Q66+Q68+Q70+Q72+Q74+Q76+Q78+Q80+Q82+Q84+Q86+Q88+Q90 -> 54.496167 | R94: =R2+R4+R6+R8+R10+R12+R14+R16+R18+R20+R22+R24+R26+R28+R30+R32+R34+R36+R38+R40+R42+R44+R46+R48+R50+R52+R54+R56+R58+R60+R62+R64+R66+R68+R70+R72+R74+R76+R78+R80+R82+R84+R86+R88+R90 -> 127.91067 | S94: =S2+S4+S6+S8+S10+S12+S14+S16+S18+S20+S22+S24+S26+S28+S30+S32+S34+S36+S38+S40+S42+S44+S46+S48+S50+S52+S54+S56+S58+S60+S62+S64+S66+S68+S70+S72+S74+S76+S78+S80+S82+S84+S86+S88+S90 -> 134.47367 | T94: =T2+T4+T6+T8+T10+T12+T14+T16+T18+T20+T22+T24+T26+T28+T30+T32+T34+T36+T38+T40+T42+T44+T46+T48+T50+T52+T54+T56+T58+T60+T62+T64+T66+T68+T70+T72+T74+T76+T78+T80+T82+T84+T86+T88+T90 -> 56.872167 | ... X94: =X2+X4+X6+X8+X10+X12+X14+X16+X18+X20+X22+X24+X26+X28+X30+X32+X34+X36+X38+X40+X42+X44+X46+X48+X50+X52+X54+X56+X58+X60+X62+X64+X66+X68+X70+X72+X74+X76+X78+X80+X82+X84+X86+X88+X90 -> 4.1441667 | Y94: =SUM(M94:X94) -> 683.62
H95: Agosto | I95: =SUM(I42:I78) -> 689.75 | M95: =M3+M5+M7+M9+M11+M13+M15+M17+M19+M21+M23+M25+M27+M29+M31+M33+M35+M37+M39+M41+M43+M45+M47+M49+M51+M53+M55+M57+M59+M61+M63+M65+M67+M69+M71+M73+M75+M77+M79+M81+M83+M85+M87+M89+M91 -> 0.98 | N95: =N3+N5+N7+N9+N11+N13+N15+N17+N19+N21+N23+N25+N27+N29+N31+N33+N35+N37+N39+N41+N43+N45+N47+N49+N51+N53+N55+N57+N59+N61+N63+N65+N67+N69+N71+N73+N75+N77+N79+N81+N83+N85+N87+N89+N91 -> 0.21 | O95: =O3+O5+O7+O9+O11+O13+O15+O17+O19+O21+O23+O25+O27+O29+O31+O33+O35+O37+O39+O41+O43+O45+O47+O49+O51+O53+O55+O57+O59+O61+O63+O65+O67+O69+O71+O73+O75+O77+O79+O81+O83+O85+O87+O89+O91 -> 9.245 | P95: =P3+P5+P7+P9+P11+P13+P15+P17+P19+P21+P23+P25+P27+P29+P31+P33+P35+P37+P39+P41+P43+P45+P47+P49+P51+P53+P55+P57+P59+P61+P63+P65+P67+P69+P71+P73+P75+P77+P79+P81+P83+P85+P87+P89+P91 -> 2.91 | Q95: =Q3+Q5+Q7+Q9+Q11+Q13+Q15+Q17+Q19+Q21+Q23+Q25+Q27+Q29+Q31+Q33+Q35+Q37+Q39+Q41+Q43+Q45+Q47+Q49+Q51+Q53+Q55+Q57+Q59+Q61+Q63+Q65+Q67+Q69+Q71+Q73+Q75+Q77+Q79+Q81+Q83+Q85+Q87+Q89+Q91 -> 10.59 | R95: =R3+R5+R7+R9+R11+R13+R15+R17+R19+R21+R23+R25+R27+R29+R31+R33+R35+R37+R39+R41+R43+R45+R47+R49+R51+R53+R55+R57+R59+R61+R63+R65+R67+R69+R71+R73+R75+R77+R79+R81+R83+R85+R87+R89+R91 -> 63.33 | S95: =S3+S5+S7+S9+S11+S13+S15+S17+S19+S21+S23+S25+S27+S29+S31+S33+S35+S37+S39+S41+S43+S45+S47+S49+S51+S53+S55+S57+S59+S61+S63+S65+S67+S69+S71+S73+S75+S77+S79+S81+S83+S85+S87+S89+S91 -> 67.4 | T95: =T3+T5+T7+T9+T11+T13+T15+T17+T19+T21+T23+T25+T27+T29+T31+T33+T35+T37+T39+T41+T43+T45+T47+T49+T51+T53+T55+T57+T59+T61+T63+T65+T67+T69+T71+T73+T75+T77+T79+T81+T83+T85+T87+T89+T91 -> 40.7 | ... X95: =X3+X5+X7+X9+X11+X13+X15+X17+X19+X21+X23+X25+X27+X29+X31+X33+X35+X37+X39+X41+X43+X45+X47+X49+X51+X53+X55+X57+X59+X61+X63+X65+X67+X69+X71+X73+X75+X77+X79+X81+X83+X85+X87+X89+X91 -> 39.99 | Y95: =SUM(M95:X95) -> 307.475
H96: Septiembre | I96: =SUM(I80:I90) -> 159.5
M97: =M94*1000000 -> 904166.67 | N97: =N94*1000000 -> 29984167 | O97: =O94*1000000 -> 1.0634867e+08 | P97: =P94*1000000 -> 87233667 | Q97: =Q94*1000000 -> 54496167 | R97: =R94*1000000 -> 1.2791067e+08 | S97: =S94*1000000 -> 1.3447367e+08 | T97: =T94*1000000 -> 56872167 | ... Y97: =Y94*1000000 -> 6.8362e+08
M98: =M95*1000000 -> 980000 | N98: =N95*1000000 -> 210000 | O98: =O95*1000000 -> 9245000 | P98: =P95*1000000 -> 2910000 | Q98: =Q95*1000000 -> 10590000 | R98: =R95*1000000 -> 63330000 | S98: =S95*1000000 -> 67400000 | T98: =T95*1000000 -> 40700000 | ... Y98: =Y95*1000000 -> 307475000
A104: Normativo | B104: SLRP para PMGD | C104: Novasource Power Services | D104: Franco Travaglini | E104: 180 | F104: 46295 | G104: Cierre | H104: 0.3 | I104: =E104*H104 -> 54

Sheet Flujo
A1: Línea | B1: Oportunidad | C1: Cliente | D1: Vendedor | E1: Ingreso esperado | F1: Cierre esperado | G1: Etapa | H1: Probabilidad | I1: Ingreso con % | J1: Nota | K1: Marzo | L1: Abril | M1: Mayo | N1: Junio | O1: Julio | P1: Agosto | Q1: Septiembre | R1: Octubre | S1: Noviembre | T1: Diciembre
A2: PAC | B2: Transelec - Retrofit de Protecciones | C2: TRANSELEC S A | D2: Kevin Fuentealba | E2: 120 | F2: 46066 | G2: Cierre 90% (Adjudicación Verbal) | H2: 1 | I2: =E2*H2 -> 120 | J2: En backlog
A3: PAC | B3: Transelec - Retrofit de Protecciones 2026 | C3: TRANSELEC S A | D3: Kevin Fuentealba | E3: 120 | F3: 46081 | G3: Cierre 70% (Preferencia) | H3: 0.7 | I3: =E3*H3 -> 84 | J3: Añadir flujo
A4: Egresos
A5: Normativo | B5: Mantenimiento | C5: Celeo | D5: Franco Travaglini | E5: 64 | F5: 46081 | G5: Cierre | H5: 0.9 | I5: =E5*H5 -> 57.6 | L5: =I5 -> 57.6
A6: Normativo | B6: 6 PMU | C6: CGE | D6: Bruno Jofré | E6: 100 | F6: 46081 | G6: Cierre | H6: 0.9 | I6: =E6*H6 -> 90 | J6: En backlog
A7: SCADA | B7: Drivers Mantos Blancos | C7: MANTOS COPPER S.A. | D7: Franco Travaglini | E7: 12 | F7: 46112 | G7: Cierre | H7: 0.5 | I7: =E7*H7 -> 6
A8: PAC | B8: Reemplazo SAS Hualpén- Transelec | C8: TRANSELEC S A | D8: Kevin Fuentealba | E8: 736 | F8: 46112 | G8: Cierre 60% (CT Cubierto) | H8: 0.6 | I8: =E8*H8 -> 441.6 | J8: Añadir flujo
A9: Egresos
A10: PAC | B10: Chilquinta - Suministro Relé NR SE Damascal | C10: Chilquinta | D10: Kevin Fuentealba | E10: 15 | F10: 46112 | G10: Cierre 60% (CT Cubierto) | H10: 0.6 | I10: =E10*H10 -> 9
A11: Normativo | B11: Visita de levantamiento | C11: Agrosuper | D11: Bruno Jofré | E11: 3 | F11: 46080 | G11: Cierre | H11: 0.9 | I11: =E11*H11 -> 2.7
A12: Normativo | B12: Acondicionamiento del SITR | C12: Mantoverde | D12: Francisco Catalan | E12: 25 | F12: 46080 | G12: Cierre | H12: 1 | I12: =E12*H12 -> 25 | J12: En backlog
A13: Normativo | B13: Implementación 2 PMU | C13: Pacific Hydro | D13: Bruno Jofré | E13: 50 | F13: 46080 | G13: Cierre | H13: 1 | I13: =E13*H13 -> 50 | J13: En backlog
A14: Normativo | B14: Implementación 2 PMU | C14: Tinguiririca | D14: Bruno Jofré | E14: 91 | F14: 46080 | G14: Cierre | H14: 1 | I14: =E14*H14 -> 91
A15: Normativo | B15: Visita de levantamiento | C15: Cementos Melon | D15: Francisco Catalan | E15: 3 | F15: 46081 | G15: Cierre 60% (CT Cubierto) | H15: 0.5 | I15: =E15*H15 -> 1.5
A16: Normativo | B16: 3 Licencias PDC | C16: Acciona | D16: Franco Travaglini | E16: 10 | F16: 46081 | G16: Cierre | H16: 0.9 | I16: =E16*H16 -> 9
A17: PAC | B17: Trabajos adicionales Diego de Almagro | C17: Chilquinta | D17: Kevin Fuentealba | E17: 30 | F17: 46112 | G17: Cierre | H17: 1 | I17: =E17*H17 -> 30 | J17: En backlog
A18: Normativo | B18: PMU La Huayca | C18: Saferay | D18: Francisco Catalan | E18: 35 | F18: 46112 | G18: Cierre 60% (CT Cubierto) | H18: 0.6 | I18: =E18*H18 -> 21
A19: Normativo | B19: Implementación 6 PMUs | C19: Inkia | D19: Franco Travaglini | E19: 220 | F19: 46112 | G19: Cierre | H19: 0.5 | I19: =E19*H19 -> 110
A20: Normativo | B20: 5 x PMU de Sonnedix + PDC | C20: Sonnedix PMU | D20: Franco Travaglini | E20: 180 | F20: 46112 | G20: Cierre 70% (Preferencia) | H20: 0.7 | I20: =E20*H20 -> 126
A21: Normativo | B21: PMU - Eletrans | C21: Eletrans | D21: Franco Travaglini | E21: 86 | F21: 46112 | G21: Cierre 70% (Preferencia) | H21: 0.7 | I21: =E21*H21 -> 60.2
A22: Normativo | B22: PMU Campo lindo y PE San Matias | C22: AES | D22: Francisco Catalan | E22: 75 | F22: 46112 | G22: Cierre 90% (Adjudicación Verbal) | H22: 0.9 | I22: =E22*H22 -> 67.5
A23: Normativo | B23: Suministro e Integración 4 x PMU y 1 x PDC centralizado | C23: Statkraft | D23: Francisco Catalan | E23: 145 | F23: 46112 | G23: Cierre 70% (Preferencia) | H23: 0.5 | I23: =E23*H23 -> 72.5
A25: Normativo | B25: Suministro 3 PMU TER - Esperanza | C25: Enorchile S.A. | D25: Francisco Catalan | E25: 73 | F25: 46112 | G25: Cierre | H25: 0.5 | I25: =E25*H25 -> 36.5
A26: Normativo | B26: Codelco Gabriela Mistral - SLRP | C26: Codelco | D26: Franco Travaglini | E26: 39 | F26: 46112 | G26: Cierre 70% (Preferencia) | H26: 0.7 | I26: =E26*H26 -> 27.3
A27: Normativo | B27: Central Huasco y Guacolda (3 PMU) + 5 integraciones | C27: Guacolda | D27: Franco Travaglini | E27: 100 | F27: 46112 | G27: Cierre 70% (Preferencia) | H27: 1 | I27: =E27*H27 -> 100 | J27: Por portal adjudicado | K27: revisar oferta 250823
A28: Egresos
A29: Normativo | B29: PMU Mantos Blancos | C29: Diego Navarrete Lucero | D29: Kevin Fuentealba | E29: 70 | F29: 46112 | G29: Cierre | H29: 0.5 | I29: =E29*H29 -> 35
A30: Normativo | B30: Modernización Servidores PDC | C30: TRANSELEC S A | D30: Franco Travaglini | E30: 206 | F30: 46112 | G30: Cierre | H30: 0.9 | I30: =E30*H30 -> 185.4
A31: SCADA | B31: Integración de 9 Protecciones al SCADA | C31: Codelco | D31: Franco Travaglini | E31: 10 | F31: 46112 | G31: Cierre 70% (Preferencia) | H31: 0.7 | I31: =E31*H31 -> 7
A32: PAC | B32: Sigma & Enaex - Retrofit de RTU | C32: Sigma | D32: Kevin Fuentealba | E32: 60 | F32: 46112 | G32: Cierre 60% (CT Cubierto) | H32: 0.3 | I32: =E32*H32 -> 18
A33: PAC | B33: Retrofit Protecciones La Huayca | C33: Enlight | D33: Kevin Fuentealba | E33: 100 | F33: 46112 | G33: Cierre | H33: 0.3 | I33: =E33*H33 -> 30
A34: PAC | B34: TECK - Capacitación de protecciones | C34: Teck | D34: Kevin Fuentealba | E34: 10 | F34: 46112 | G34: Cierre | H34: 0.3 | I34: =E34*H34 -> 3
A35: PAC | B35: Tecnored - Suministro de Relé NR | C35: Tecnored | D35: Kevin Fuentealba | E35: 20 | F35: 46112 | G35: Cierre | H35: 0.05 | I35: =E35*H35 -> 1
A36: PAC | B36: Servicios Reconectadores Fase 1 | C36: Chilquinta Distribución | D36: Kevin Fuentealba | E36: 50 | F36: 46112 | G36: Cierre 90% (Adjudicación Verbal) | H36: 0.9 | I36: =E36*H36 -> 45
K37: =SUM(K2:K36) -> 0 | L37: =SUM(L2:L36) -> 57.6 | M37: =SUM(M2:M36) -> 0 | N37: =SUM(N2:N36) -> 0 | O37: =SUM(O2:O36) -> 0 | P37: =SUM(P2:P36) -> 0 | Q37: =SUM(Q2:Q36) -> 0 | R37: =SUM(R2:R36) -> 0 | ... T37: =SUM(T2:T36) -> 0
H38: Enero | I38: ='Proyección Q1 (Enero)'!J22 -> 292
H39: Febrero | I39: =SUM(I2:I17) -> 1017.4
H40: Marzo | I40: =SUM(I18:I36) -> 945.4
H41: Total | I41: =SUM(I38:I40) -> 2254.8
A45: Normativo | B45: Implementación 18 PMUs | C45: SAESA | D45: Bruno Jofré | E45: 285 | F45: 46173 | G45: Cotización | H45: 0.3 | I45: =E45*H45 -> 85.5
A46: Normativo | B46: 4 PMU | C46: Enor | D46: Bruno Jofré | E46: =35*4 -> 140 | F46: Abril | G46: Cotización | H46: 0.5 | I46: =E46*H46 -> 70
A47: Egresos
